{"pl4-ar9":{"scrydex":{"holofoil":{"raw":37.24,"psa10":308.37}},"tcgplayer":null,"cardmarket":null},"pl4-ar8":{"scrydex":{"holofoil":{"raw":29.31,"psa10":1972.55}},"tcgplayer":null,"cardmarket":null},"pl4-ar7":{"scrydex":{"holofoil":{"raw":28.01,"psa10":5983.27}},"tcgplayer":null,"cardmarket":null},"pl4-ar6":{"scrydex":{"holofoil":{"raw":19.62,"psa10":292.95}},"tcgplayer":null,"cardmarket":null},"pl4-ar5":{"scrydex":{"holofoil":{"raw":32.84,"psa10":2000}},"tcgplayer":null,"cardmarket":null},"pl4-ar4":{"scrydex":{"holofoil":{"raw":46.76,"psa10":449.76}},"tcgplayer":null,"cardmarket":null},"pl4-ar3":{"scrydex":{"holofoil":{"raw":29.23,"psa10":290.56}},"tcgplayer":null,"cardmarket":null},"pl4-ar2":{"scrydex":{"holofoil":{"raw":32.06,"psa10":285.17}},"tcgplayer":null,"cardmarket":null},"pl4-ar1":{"scrydex":{"holofoil":{"raw":46.16,"psa10":998.93}},"tcgplayer":null,"cardmarket":null},"pl4-sh12":{"scrydex":{"reverseHolofoil":{"raw":128.52,"psa10":3500}},"tcgplayer":null,"cardmarket":null},"pl4-sh11":{"scrydex":{"reverseHolofoil":{"raw":185.78,"psa10":5204.02}},"tcgplayer":null,"cardmarket":null},"pl4-sh10":{"scrydex":{"reverseHolofoil":{"raw":77.84}},"tcgplayer":null,"cardmarket":null},"pl4-99":{"scrydex":{"holofoil":{"raw":29.58,"psa10":481.68}},"tcgplayer":null,"cardmarket":null},"pl4-98":{"scrydex":{"holofoil":{"raw":71.62,"psa10":3607.35}},"tcgplayer":null,"cardmarket":null},"pl4-97":{"scrydex":{"holofoil":{"raw":320.66,"psa10":7973.22,"ace10":337.38}},"tcgplayer":null,"cardmarket":null},"pl4-96":{"scrydex":{"holofoil":{"raw":40.03,"psa10":1830}},"tcgplayer":null,"cardmarket":null},"pl4-95":{"scrydex":{"holofoil":{"raw":66.46,"psa10":50}},"tcgplayer":null,"cardmarket":null},"pl4-94":{"scrydex":{"holofoil":{"raw":42.54,"psa10":2942.99}},"tcgplayer":null,"cardmarket":null},"pl4-93":{"scrydex":{"normal":{"raw":0.44},"reverseHolofoil":{"raw":1.05}},"tcgplayer":null,"cardmarket":null},"pl4-92":{"scrydex":{"normal":{"raw":0.33},"reverseHolofoil":{"raw":1.87,"psa10":28}},"tcgplayer":null,"cardmarket":null},"pl4-91":{"scrydex":{"normal":{"raw":0.42,"psa10":45},"reverseHolofoil":{"raw":2.24}},"tcgplayer":null,"cardmarket":null},"pl4-90":{"scrydex":{"normal":{"raw":0.39},"reverseHolofoil":{"raw":1.5}},"tcgplayer":null,"cardmarket":null},"pl4-89":{"scrydex":{"normal":{"raw":0.26},"reverseHolofoil":{"raw":0.69}},"tcgplayer":null,"cardmarket":null},"pl4-88":{"scrydex":{"normal":{"raw":0.61},"reverseHolofoil":{"raw":3,"psa10":17}},"tcgplayer":null,"cardmarket":null},"pl4-87":{"scrydex":{"normal":{"raw":1},"reverseHolofoil":{"raw":2.3,"psa10":9},"leagueStamp":{"raw":2.13},"michaelPramawat":{"raw":2.95},"mychaelBryan":{"raw":1},"yukaFurusawa":{"raw":1}},"tcgplayer":null,"cardmarket":null},"pl4-86":{"scrydex":{"normal":{"raw":0.23},"reverseHolofoil":{"raw":0.89}},"tcgplayer":null,"cardmarket":null},"pl4-85":{"scrydex":{"normal":{"raw":0.57},"reverseHolofoil":{"raw":1.94,"psa10":24}},"tcgplayer":null,"cardmarket":null},"pl4-84":{"scrydex":{"normal":{"raw":0.23},"reverseHolofoil":{"raw":0.42}},"tcgplayer":null,"cardmarket":null},"pl4-83":{"scrydex":{"normal":{"raw":0.37},"reverseHolofoil":{"raw":0.96}},"tcgplayer":null,"cardmarket":null},"pl4-82":{"scrydex":{"normal":{"raw":0.52},"reverseHolofoil":{"raw":2.04}},"tcgplayer":null,"cardmarket":null},"pl4-81":{"scrydex":{"normal":{"raw":0.35},"reverseHolofoil":{"raw":1.93}},"tcgplayer":null,"cardmarket":null},"pl4-80":{"scrydex":{"normal":{"raw":0.29},"reverseHolofoil":{"raw":1.54}},"tcgplayer":null,"cardmarket":null},"pl4-79":{"scrydex":{"normal":{"raw":0.63},"reverseHolofoil":{"raw":8.25}},"tcgplayer":null,"cardmarket":null},"pl4-78":{"scrydex":{"normal":{"raw":1.06,"psa10":17},"reverseHolofoil":{"raw":15.89,"psa10":13}},"tcgplayer":null,"cardmarket":null},"pl4-77":{"scrydex":{"normal":{"raw":0.4,"psa10":40},"reverseHolofoil":{"raw":2.3}},"tcgplayer":null,"cardmarket":null},"pl4-76":{"scrydex":{"normal":{"raw":0.33},"reverseHolofoil":{"raw":2.97}},"tcgplayer":null,"cardmarket":null},"pl4-75":{"scrydex":{"normal":{"raw":0.96},"reverseHolofoil":{"raw":0.1}},"tcgplayer":null,"cardmarket":null},"pl4-74":{"scrydex":{"normal":{"raw":0.41},"reverseHolofoil":{"raw":6.07,"psa10":3495.66}},"tcgplayer":null,"cardmarket":null},"pl4-73":{"scrydex":{"normal":{"raw":0.41},"reverseHolofoil":{"raw":4.17}},"tcgplayer":null,"cardmarket":null},"pl4-72":{"scrydex":{"normal":{"raw":0.33},"reverseHolofoil":{"raw":5,"psa10":20}},"tcgplayer":null,"cardmarket":null},"pl4-71":{"scrydex":{"normal":{"raw":6.13,"psa10":2801,"ace10":40.43},"reverseHolofoil":{"raw":27.5}},"tcgplayer":null,"cardmarket":null},"pl4-70":{"scrydex":{"normal":{"raw":0.34},"reverseHolofoil":{"raw":5}},"tcgplayer":null,"cardmarket":null},"pl4-69":{"scrydex":{"normal":{"raw":0.39},"reverseHolofoil":{"raw":1}},"tcgplayer":null,"cardmarket":null},"pl4-68":{"scrydex":{"normal":{"raw":0.3},"reverseHolofoil":{"raw":1.24}},"tcgplayer":null,"cardmarket":null},"pl4-67":{"scrydex":{"normal":{"raw":0.55},"reverseHolofoil":{"raw":1.71}},"tcgplayer":null,"cardmarket":null},"pl4-66":{"scrydex":{"normal":{"raw":0.3},"reverseHolofoil":{"raw":2.25,"psa10":32.47}},"tcgplayer":null,"cardmarket":null},"pl4-65":{"scrydex":{"normal":{"raw":0.35},"reverseHolofoil":{"raw":1.29}},"tcgplayer":null,"cardmarket":null},"pl4-64":{"scrydex":{"normal":{"raw":0.45,"psa10":25},"reverseHolofoil":{"raw":19.99}},"tcgplayer":null,"cardmarket":null},"pl4-63":{"scrydex":{"normal":{"raw":0.23},"reverseHolofoil":{"raw":0.78,"psa10":24}},"tcgplayer":null,"cardmarket":null},"pl4-62":{"scrydex":{"normal":{"raw":0.36},"reverseHolofoil":{"raw":1.24,"psa10":16}},"tcgplayer":null,"cardmarket":null},"pl4-61":{"scrydex":{"normal":{"raw":0.42},"reverseHolofoil":{"raw":9.77}},"tcgplayer":null,"cardmarket":null},"pl4-60":{"scrydex":{"normal":{"raw":0.74},"reverseHolofoil":{"raw":8.54,"psa10":15}},"tcgplayer":null,"cardmarket":null},"pl4-59":{"scrydex":{"normal":{"raw":2.08,"psa10":299.99},"reverseHolofoil":{"raw":75,"psa10":185}},"tcgplayer":null,"cardmarket":null},"pl4-58":{"scrydex":{"normal":{"raw":0.4},"reverseHolofoil":{"raw":1.58,"psa10":39.99}},"tcgplayer":null,"cardmarket":null},"pl4-57":{"scrydex":{"normal":{"raw":0.62},"reverseHolofoil":{"raw":6.35}},"tcgplayer":null,"cardmarket":null},"pl4-56":{"scrydex":{"normal":{"raw":0.31},"reverseHolofoil":{"raw":1.43}},"tcgplayer":null,"cardmarket":null},"pl4-55":{"scrydex":{"normal":{"raw":0.4},"reverseHolofoil":{"raw":2.93,"psa10":74.95}},"tcgplayer":null,"cardmarket":null},"pl4-54":{"scrydex":{"normal":{"raw":0.34},"reverseHolofoil":{"raw":1.76}},"tcgplayer":null,"cardmarket":null},"pl4-53":{"scrydex":{"normal":{"raw":0.46},"reverseHolofoil":{"raw":2.18}},"tcgplayer":null,"cardmarket":null},"pl4-52":{"scrydex":{"normal":{"raw":0.39},"reverseHolofoil":{"raw":1.06,"psa10":1045.61}},"tcgplayer":null,"cardmarket":null},"pl4-51":{"scrydex":{"normal":{"raw":0.43},"reverseHolofoil":{"raw":1.27,"psa10":8}},"tcgplayer":null,"cardmarket":null},"pl4-50":{"scrydex":{"normal":{"raw":0.33},"reverseHolofoil":{"raw":0.85}},"tcgplayer":null,"cardmarket":null},"pl4-49":{"scrydex":{"normal":{"raw":0.35},"reverseHolofoil":{"raw":0.77}},"tcgplayer":null,"cardmarket":null},"pl4-48":{"scrydex":{"normal":{"raw":0.43},"reverseHolofoil":{"raw":1.7}},"tcgplayer":null,"cardmarket":null},"pl4-47":{"scrydex":{"normal":{"raw":0.58},"reverseHolofoil":{"raw":1.62,"psa10":59}},"tcgplayer":null,"cardmarket":null},"pl4-46":{"scrydex":{"normal":{"raw":0.79},"reverseHolofoil":{"raw":15.42,"psa10":560}},"tcgplayer":null,"cardmarket":null},"pl4-45":{"scrydex":{"normal":{"raw":0.46},"reverseHolofoil":{"raw":0.82}},"tcgplayer":null,"cardmarket":null},"pl4-44":{"scrydex":{"normal":{"raw":0.42},"reverseHolofoil":{"raw":1.64}},"tcgplayer":null,"cardmarket":null},"pl4-43":{"scrydex":{"normal":{"raw":0.42},"reverseHolofoil":{"raw":1.26,"psa10":28}},"tcgplayer":null,"cardmarket":null},"pl4-42":{"scrydex":{"normal":{"raw":1.17,"psa10":100},"reverseHolofoil":{"raw":14.72}},"tcgplayer":null,"cardmarket":null},"pl4-41":{"scrydex":{"normal":{"raw":7.5,"psa10":49.87},"reverseHolofoil":{"raw":10.98,"psa10":53}},"tcgplayer":null,"cardmarket":null},"pl4-40":{"scrydex":{"normal":{"raw":0.78},"reverseHolofoil":{"raw":2.2,"psa10":399.32}},"tcgplayer":null,"cardmarket":null},"pl4-39":{"scrydex":{"normal":{"raw":0.59,"psa10":30},"reverseHolofoil":{"raw":1.48,"psa10":39.99}},"tcgplayer":null,"cardmarket":null},"pl4-38":{"scrydex":{"normal":{"raw":0.74},"reverseHolofoil":{"raw":1.73}},"tcgplayer":null,"cardmarket":null},"pl4-37":{"scrydex":{"normal":{"raw":1.05,"psa10":45},"reverseHolofoil":{"raw":2.09}},"tcgplayer":null,"cardmarket":null},"pl4-36":{"scrydex":{"normal":{"raw":1.26},"reverseHolofoil":{"raw":9.72,"psa10":24.99}},"tcgplayer":null,"cardmarket":null},"pl4-35":{"scrydex":{"normal":{"raw":1.46,"psa10":85},"reverseHolofoil":{"raw":13.45,"psa10":30.12}},"tcgplayer":null,"cardmarket":null},"pl4-34":{"scrydex":{"normal":{"raw":0.29},"reverseHolofoil":{"raw":1.06}},"tcgplayer":null,"cardmarket":null},"pl4-33":{"scrydex":{"normal":{"raw":0.37},"reverseHolofoil":{"raw":0.98}},"tcgplayer":null,"cardmarket":null},"pl4-32":{"scrydex":{"normal":{"raw":5.56},"reverseHolofoil":{"raw":9.41,"psa10":12},"leagueStamp":{"raw":5},"michaelPramawat":{"raw":3.23}},"tcgplayer":null,"cardmarket":null},"pl4-31":{"scrydex":{"normal":{"raw":2.26},"reverseHolofoil":{"raw":3.99,"psa10":36}},"tcgplayer":null,"cardmarket":null},"pl4-30":{"scrydex":{"normal":{"raw":2.64},"reverseHolofoil":{"raw":5.55,"psa10":500}},"tcgplayer":null,"cardmarket":null},"pl4-29":{"scrydex":{"normal":{"raw":0.81},"reverseHolofoil":{"raw":1.79}},"tcgplayer":null,"cardmarket":null},"pl4-28":{"scrydex":{"normal":{"raw":1.31,"psa10":12.79},"reverseHolofoil":{"raw":3.97}},"tcgplayer":null,"cardmarket":null},"pl4-27":{"scrydex":{"normal":{"raw":4.64,"psa10":365},"reverseHolofoil":{"raw":19.34,"psa10":455},"expansionStamp":{"raw":52.98}},"tcgplayer":null,"cardmarket":null},"pl4-26":{"scrydex":{"normal":{"raw":1.74},"reverseHolofoil":{"raw":7.39,"psa10":2500}},"tcgplayer":null,"cardmarket":null},"pl4-25":{"scrydex":{"normal":{"raw":10.54},"reverseHolofoil":{"raw":23.99,"psa10":2000}},"tcgplayer":null,"cardmarket":null},"pl4-24":{"scrydex":{"normal":{"raw":0.88},"reverseHolofoil":{"raw":1.82}},"tcgplayer":null,"cardmarket":null},"pl4-23":{"scrydex":{"normal":{"raw":1.72},"reverseHolofoil":{"raw":4.1,"psa10":30}},"tcgplayer":null,"cardmarket":null},"pl4-22":{"scrydex":{"normal":{"raw":0.59},"reverseHolofoil":{"raw":3.7,"psa10":279.1}},"tcgplayer":null,"cardmarket":null},"pl4-21":{"scrydex":{"normal":{"raw":1.87},"reverseHolofoil":{"raw":6.36}},"tcgplayer":null,"cardmarket":null},"pl4-20":{"scrydex":{"normal":{"raw":0.71},"reverseHolofoil":{"raw":0.96,"psa10":30}},"tcgplayer":null,"cardmarket":null},"pl4-19":{"scrydex":{"normal":{"raw":1.72},"reverseHolofoil":{"raw":12.4,"psa10":41}},"tcgplayer":null,"cardmarket":null},"pl4-18":{"scrydex":{"normal":{"raw":0.87},"reverseHolofoil":{"raw":2.73,"psa10":10}},"tcgplayer":null,"cardmarket":null},"pl4-17":{"scrydex":{"normal":{"raw":44.13,"psa10":10000,"ace10":46.95},"reverseHolofoil":{"raw":108.49,"psa10":3550}},"tcgplayer":null,"cardmarket":null},"pl4-16":{"scrydex":{"normal":{"raw":32.71,"psa10":2827.44,"ace10":39.91},"reverseHolofoil":{"raw":76.65,"psa10":235,"ace10":48.24}},"tcgplayer":null,"cardmarket":null},"pl4-15":{"scrydex":{"normal":{"raw":5.59,"psa10":47.99},"reverseHolofoil":{"raw":12.47}},"tcgplayer":null,"cardmarket":null},"pl4-14":{"scrydex":{"normal":{"raw":0.59},"reverseHolofoil":{"raw":1.02,"psa10":16}},"tcgplayer":null,"cardmarket":null},"pl4-13":{"scrydex":{"normal":{"raw":2.04,"psa10":49.99},"reverseHolofoil":{"raw":6.97,"psa10":125}},"tcgplayer":null,"cardmarket":null},"pl4-12":{"scrydex":{"holofoil":{"raw":13.43,"psa10":520.16},"reverseHolofoil":{"raw":23}},"tcgplayer":null,"cardmarket":null},"pl4-11":{"scrydex":{"holofoil":{"raw":2.62,"psa10":271},"reverseHolofoil":{"raw":5.79}},"tcgplayer":null,"cardmarket":null},"pl4-10":{"scrydex":{"normal":{"raw":0.74},"holofoil":{"raw":4.01,"psa10":70.37},"reverseHolofoil":{"raw":2.19}},"tcgplayer":null,"cardmarket":null},"pl4-9":{"scrydex":{"normal":{"raw":1.36,"psa10":25},"holofoil":{"raw":3.2,"psa10":25.48},"reverseHolofoil":{"raw":2.96}},"tcgplayer":null,"cardmarket":null},"pl4-8":{"scrydex":{"holofoil":{"raw":7.18,"psa10":679.3},"reverseHolofoil":{"raw":8.31}},"tcgplayer":null,"cardmarket":null},"pl4-7":{"scrydex":{"holofoil":{"raw":1.51,"psa10":60.24},"reverseHolofoil":{"raw":2.69}},"tcgplayer":null,"cardmarket":null},"pl4-6":{"scrydex":{"holofoil":{"raw":2.93,"psa10":100},"reverseHolofoil":{"raw":2.06}},"tcgplayer":null,"cardmarket":null},"pl4-5":{"scrydex":{"normal":{"raw":5.74},"holofoil":{"raw":5.15,"psa10":299.47},"reverseHolofoil":{"raw":5.4}},"tcgplayer":null,"cardmarket":null},"pl4-4":{"scrydex":{"holofoil":{"raw":13.19,"psa10":1318.81},"reverseHolofoil":{"raw":11.7}},"tcgplayer":null,"cardmarket":null},"pl4-3":{"scrydex":{"holofoil":{"raw":3.29,"psa10":82.08},"reverseHolofoil":{"raw":3.6}},"tcgplayer":null,"cardmarket":null},"pl4-2":{"scrydex":{"holofoil":{"raw":5.13,"psa10":244},"reverseHolofoil":{"raw":5.2}},"tcgplayer":null,"cardmarket":null},"pl4-1":{"scrydex":{"holofoil":{"raw":54.9,"psa10":232.88,"ace10":423.31},"reverseHolofoil":{"raw":52.62},"crackedIceHolofoil":{"raw":70.45}},"tcgplayer":null,"cardmarket":null}}