{"sv8pt5-180":{"scrydex":{"holofoil":{"raw":9.11,"psa10":96,"ace10":38.89}},"tcgplayer":null,"cardmarket":null},"sv8pt5-179":{"scrydex":{"holofoil":{"raw":62.41,"psa10":365.21}},"tcgplayer":null,"cardmarket":null},"sv8pt5-178":{"scrydex":{"holofoil":{"raw":7.25,"psa10":61.86}},"tcgplayer":null,"cardmarket":null},"sv8pt5-177":{"scrydex":{"holofoil":{"raw":7.54,"psa10":85.56}},"tcgplayer":null,"cardmarket":null},"sv8pt5-176":{"scrydex":{"holofoil":{"raw":4.89,"psa10":57.24}},"tcgplayer":null,"cardmarket":null},"sv8pt5-175":{"scrydex":{"holofoil":{"raw":28.65,"psa10":84.13}},"tcgplayer":null,"cardmarket":null},"sv8pt5-174":{"scrydex":{"holofoil":{"raw":20.98,"psa10":59.88}},"tcgplayer":null,"cardmarket":null},"sv8pt5-173":{"scrydex":{"holofoil":{"raw":26.28,"psa10":83.36,"ace10":48.21}},"tcgplayer":null,"cardmarket":null},"sv8pt5-172":{"scrydex":{"holofoil":{"raw":17.5,"psa10":81.42,"ace10":33.56}},"tcgplayer":null,"cardmarket":null},"sv8pt5-171":{"scrydex":{"holofoil":{"raw":32.35,"psa10":63.4,"ace10":39.61}},"tcgplayer":null,"cardmarket":null},"sv8pt5-170":{"scrydex":{"holofoil":{"raw":15.4,"psa10":46.11}},"tcgplayer":null,"cardmarket":null},"sv8pt5-169":{"scrydex":{"holofoil":{"raw":35.14,"psa10":99.24,"ace10":102.66}},"tcgplayer":null,"cardmarket":null},"sv8pt5-168":{"scrydex":{"holofoil":{"raw":62,"psa10":220.42,"ace10":177.81}},"tcgplayer":null,"cardmarket":null},"sv8pt5-167":{"scrydex":{"holofoil":{"raw":193.36,"psa10":625.08,"ace10":282.75}},"tcgplayer":null,"cardmarket":null},"sv8pt5-166":{"scrydex":{"holofoil":{"raw":64.22,"psa10":182.29,"ace10":130.5}},"tcgplayer":null,"cardmarket":null},"sv8pt5-165":{"scrydex":{"holofoil":{"raw":112.3,"psa10":229.76,"ace10":152.47}},"tcgplayer":null,"cardmarket":null},"sv8pt5-164":{"scrydex":{"holofoil":{"raw":42.1,"psa10":188.63,"ace10":107}},"tcgplayer":null,"cardmarket":null},"sv8pt5-163":{"scrydex":{"holofoil":{"raw":30.37,"psa10":69.3}},"tcgplayer":null,"cardmarket":null},"sv8pt5-162":{"scrydex":{"holofoil":{"raw":158.41,"psa10":758.07,"ace10":470.96}},"tcgplayer":null,"cardmarket":null},"sv8pt5-161":{"scrydex":{"holofoil":{"raw":1480.42,"psa10":4900.66,"ace10":2443.5}},"tcgplayer":null,"cardmarket":null},"sv8pt5-160":{"scrydex":{"holofoil":{"raw":15.3,"psa10":54.2}},"tcgplayer":null,"cardmarket":null},"sv8pt5-159":{"scrydex":{"holofoil":{"raw":22.92,"psa10":73.75}},"tcgplayer":null,"cardmarket":null},"sv8pt5-158":{"scrydex":{"holofoil":{"raw":33.82,"psa10":80.37}},"tcgplayer":null,"cardmarket":null},"sv8pt5-157":{"scrydex":{"holofoil":{"raw":44.93,"psa10":168.37,"ace10":79.57}},"tcgplayer":null,"cardmarket":null},"sv8pt5-156":{"scrydex":{"holofoil":{"raw":388.12,"psa10":1470.04,"ace10":708.62}},"tcgplayer":null,"cardmarket":null},"sv8pt5-155":{"scrydex":{"holofoil":{"raw":279.1,"psa10":1021.03,"ace10":491.47}},"tcgplayer":null,"cardmarket":null},"sv8pt5-154":{"scrydex":{"holofoil":{"raw":35.92,"psa10":86.84,"ace10":50.62}},"tcgplayer":null,"cardmarket":null},"sv8pt5-153":{"scrydex":{"holofoil":{"raw":162.99,"psa10":544.28,"ace10":282.99}},"tcgplayer":null,"cardmarket":null},"sv8pt5-152":{"scrydex":{"holofoil":{"raw":14.32,"psa10":65.42}},"tcgplayer":null,"cardmarket":null},"sv8pt5-151":{"scrydex":{"holofoil":{"raw":43,"psa10":163.98}},"tcgplayer":null,"cardmarket":null},"sv8pt5-150":{"scrydex":{"holofoil":{"raw":215.09,"psa10":725.33,"ace10":323.88}},"tcgplayer":null,"cardmarket":null},"sv8pt5-149":{"scrydex":{"holofoil":{"raw":219.92,"psa10":1066.68,"ace10":418.89}},"tcgplayer":null,"cardmarket":null},"sv8pt5-148":{"scrydex":{"holofoil":{"raw":19.52,"psa10":85.1}},"tcgplayer":null,"cardmarket":null},"sv8pt5-147":{"scrydex":{"holofoil":{"raw":93.67,"psa10":240.06,"ace10":118.07}},"tcgplayer":null,"cardmarket":null},"sv8pt5-146":{"scrydex":{"holofoil":{"raw":176.86,"psa10":540.78,"ace10":385.59}},"tcgplayer":null,"cardmarket":null},"sv8pt5-145":{"scrydex":{"holofoil":{"raw":21.68,"psa10":82.24}},"tcgplayer":null,"cardmarket":null},"sv8pt5-144":{"scrydex":{"holofoil":{"raw":272.93,"psa10":839.35,"ace10":388.82}},"tcgplayer":null,"cardmarket":null},"sv8pt5-143":{"scrydex":{"holofoil":{"raw":0.52,"psa10":40.56}},"tcgplayer":null,"cardmarket":null},"sv8pt5-142":{"scrydex":{"holofoil":{"raw":0.75,"psa10":38.86}},"tcgplayer":null,"cardmarket":null},"sv8pt5-141":{"scrydex":{"holofoil":{"raw":0.58,"psa10":41.04}},"tcgplayer":null,"cardmarket":null},"sv8pt5-140":{"scrydex":{"holofoil":{"raw":0.83,"psa10":37.93}},"tcgplayer":null,"cardmarket":null},"sv8pt5-139":{"scrydex":{"holofoil":{"raw":0.93,"psa10":32.77}},"tcgplayer":null,"cardmarket":null},"sv8pt5-138":{"scrydex":{"holofoil":{"raw":0.55,"psa10":22.82}},"tcgplayer":null,"cardmarket":null},"sv8pt5-137":{"scrydex":{"holofoil":{"raw":1,"psa10":63.67,"ace10":50.74}},"tcgplayer":null,"cardmarket":null},"sv8pt5-136":{"scrydex":{"holofoil":{"raw":1.03,"psa10":44.29}},"tcgplayer":null,"cardmarket":null},"sv8pt5-135":{"scrydex":{"holofoil":{"raw":0.63,"psa10":23.82,"ace10":13.64}},"tcgplayer":null,"cardmarket":null},"sv8pt5-134":{"scrydex":{"holofoil":{"raw":0.69,"psa10":28.92}},"tcgplayer":null,"cardmarket":null},"sv8pt5-133":{"scrydex":{"holofoil":{"raw":0.75,"psa10":26.17}},"tcgplayer":null,"cardmarket":null},"sv8pt5-132":{"scrydex":{"holofoil":{"raw":0.62,"psa10":28.2}},"tcgplayer":null,"cardmarket":null},"sv8pt5-131":{"scrydex":{"holofoil":{"raw":0.36,"psa10":17.51}},"tcgplayer":null,"cardmarket":null},"sv8pt5-130":{"scrydex":{"normal":{"raw":0.02},"reverseHolofoil":{"raw":0.12,"psa10":14.5},"pokeBallReverseHolofoil":{"raw":0.3}},"tcgplayer":null,"cardmarket":null},"sv8pt5-129":{"scrydex":{"holofoil":{"raw":0.43,"psa10":10.43,"ace10":20.5},"playPokemonStampHolofoil":{"raw":2.03}},"tcgplayer":null,"cardmarket":null},"sv8pt5-128":{"scrydex":{"holofoil":{"raw":0.33,"psa10":30.02}},"tcgplayer":null,"cardmarket":null},"sv8pt5-127":{"scrydex":{"normal":{"raw":0.11},"reverseHolofoil":{"raw":0.2,"psa10":9.96},"pokeBallReverseHolofoil":{"raw":0.25}},"tcgplayer":null,"cardmarket":null},"sv8pt5-126":{"scrydex":{"normal":{"raw":0.04},"reverseHolofoil":{"raw":0.11},"pokeBallReverseHolofoil":{"raw":0.33}},"tcgplayer":null,"cardmarket":null},"sv8pt5-125":{"scrydex":{"normal":{"raw":0.09},"reverseHolofoil":{"raw":0.11,"psa10":40},"pokeBallReverseHolofoil":{"raw":0.29}},"tcgplayer":null,"cardmarket":null},"sv8pt5-124":{"scrydex":{"normal":{"raw":0.14},"reverseHolofoil":{"raw":0.16,"psa10":7},"pokeBallReverseHolofoil":{"raw":0.28}},"tcgplayer":null,"cardmarket":null},"sv8pt5-123":{"scrydex":{"normal":{"raw":0.06},"reverseHolofoil":{"raw":0.12},"pokeBallReverseHolofoil":{"raw":0.28}},"tcgplayer":null,"cardmarket":null},"sv8pt5-122":{"scrydex":{"normal":{"raw":0.12},"reverseHolofoil":{"raw":0.17,"psa10":22.93},"pokeBallReverseHolofoil":{"raw":0.38}},"tcgplayer":null,"cardmarket":null},"sv8pt5-121":{"scrydex":{"normal":{"raw":0.12},"reverseHolofoil":{"raw":0.23,"psa10":23},"pokeBallReverseHolofoil":{"raw":0.37}},"tcgplayer":null,"cardmarket":null},"sv8pt5-120":{"scrydex":{"normal":{"raw":0.03,"psa10":8.5},"reverseHolofoil":{"raw":0.12},"pokeBallReverseHolofoil":{"raw":0.24}},"tcgplayer":null,"cardmarket":null},"sv8pt5-119":{"scrydex":{"holofoil":{"raw":0.6,"psa10":40}},"tcgplayer":null,"cardmarket":null},"sv8pt5-118":{"scrydex":{"normal":{"raw":0.06,"psa10":35},"reverseHolofoil":{"raw":0.17},"pokeBallReverseHolofoil":{"raw":0.24}},"tcgplayer":null,"cardmarket":null},"sv8pt5-117":{"scrydex":{"holofoil":{"raw":0.51,"psa10":40}},"tcgplayer":null,"cardmarket":null},"sv8pt5-116":{"scrydex":{"holofoil":{"raw":0.75,"psa10":63.2},"playPokemonStampHolofoil":{"raw":18.13}},"tcgplayer":null,"cardmarket":null},"sv8pt5-115":{"scrydex":{"normal":{"raw":0.13},"reverseHolofoil":{"raw":0.2,"psa10":28.05},"pokeBallReverseHolofoil":{"raw":0.35}},"tcgplayer":null,"cardmarket":null},"sv8pt5-114":{"scrydex":{"normal":{"raw":0.05},"reverseHolofoil":{"raw":0.13,"psa10":54.5},"pokeBallReverseHolofoil":{"raw":0.26}},"tcgplayer":null,"cardmarket":null},"sv8pt5-113":{"scrydex":{"normal":{"raw":0.1},"reverseHolofoil":{"raw":0.19,"psa10":11.99},"pokeBallReverseHolofoil":{"raw":0.29}},"tcgplayer":null,"cardmarket":null},"sv8pt5-112":{"scrydex":{"normal":{"raw":0.14,"psa10":57},"reverseHolofoil":{"raw":0.22,"psa10":200},"pokeBallReverseHolofoil":{"raw":0.27}},"tcgplayer":null,"cardmarket":null},"sv8pt5-111":{"scrydex":{"normal":{"raw":0.08},"reverseHolofoil":{"raw":0.18,"psa10":7.99},"pokeBallReverseHolofoil":{"raw":0.24}},"tcgplayer":null,"cardmarket":null},"sv8pt5-110":{"scrydex":{"normal":{"raw":0.15},"reverseHolofoil":{"raw":0.18,"psa10":49.93},"pokeBallReverseHolofoil":{"raw":0.32}},"tcgplayer":null,"cardmarket":null},"sv8pt5-109":{"scrydex":{"normal":{"raw":0.05,"psa10":45.6},"reverseHolofoil":{"raw":0.16,"psa10":25},"pokeBallReverseHolofoil":{"raw":0.25}},"tcgplayer":null,"cardmarket":null},"sv8pt5-108":{"scrydex":{"normal":{"raw":0.11},"reverseHolofoil":{"raw":0.2,"psa10":11.97},"pokeBallReverseHolofoil":{"raw":0.39}},"tcgplayer":null,"cardmarket":null},"sv8pt5-107":{"scrydex":{"normal":{"raw":0.06},"reverseHolofoil":{"raw":0.18,"psa10":15.5},"pokeBallReverseHolofoil":{"raw":0.27}},"tcgplayer":null,"cardmarket":null},"sv8pt5-106":{"scrydex":{"normal":{"raw":0.22,"psa10":8.74},"reverseHolofoil":{"raw":0.24},"pokeBallReverseHolofoil":{"raw":0.4}},"tcgplayer":null,"cardmarket":null},"sv8pt5-105":{"scrydex":{"normal":{"raw":0.2},"reverseHolofoil":{"raw":0.26,"psa10":8},"pokeBallReverseHolofoil":{"raw":0.58}},"tcgplayer":null,"cardmarket":null},"sv8pt5-104":{"scrydex":{"normal":{"raw":0.14},"reverseHolofoil":{"raw":0.23,"psa10":40},"pokeBallReverseHolofoil":{"raw":0.31}},"tcgplayer":null,"cardmarket":null},"sv8pt5-103":{"scrydex":{"normal":{"raw":0.12},"reverseHolofoil":{"raw":0.23,"psa10":22.36},"pokeBallReverseHolofoil":{"raw":0.32}},"tcgplayer":null,"cardmarket":null},"sv8pt5-102":{"scrydex":{"normal":{"raw":0.11},"reverseHolofoil":{"raw":0.19,"psa10":42.99},"pokeBallReverseHolofoil":{"raw":0.81}},"tcgplayer":null,"cardmarket":null},"sv8pt5-101":{"scrydex":{"normal":{"raw":0.21,"psa10":44},"reverseHolofoil":{"raw":0.29},"pokeBallReverseHolofoil":{"raw":0.6}},"tcgplayer":null,"cardmarket":null},"sv8pt5-100":{"scrydex":{"normal":{"raw":0.06},"reverseHolofoil":{"raw":0.14,"psa10":49.99},"pokeBallReverseHolofoil":{"raw":0.29}},"tcgplayer":null,"cardmarket":null},"sv8pt5-99":{"scrydex":{"normal":{"raw":0.05},"reverseHolofoil":{"raw":0.11},"pokeBallReverseHolofoil":{"raw":0.26}},"tcgplayer":null,"cardmarket":null},"sv8pt5-98":{"scrydex":{"normal":{"raw":0.05},"reverseHolofoil":{"raw":0.13,"psa10":48},"pokeBallReverseHolofoil":{"raw":0.29}},"tcgplayer":null,"cardmarket":null},"sv8pt5-97":{"scrydex":{"normal":{"raw":0.03},"reverseHolofoil":{"raw":0.08,"psa10":30},"pokeBallReverseHolofoil":{"raw":0.24}},"tcgplayer":null,"cardmarket":null},"sv8pt5-96":{"scrydex":{"normal":{"raw":0.06},"reverseHolofoil":{"raw":0.17,"psa10":50},"pokeBallReverseHolofoil":{"raw":0.3}},"tcgplayer":null,"cardmarket":null},"sv8pt5-95":{"scrydex":{"normal":{"raw":0.13,"psa10":15.99},"reverseHolofoil":{"raw":0.18,"psa10":9.95},"pokeBallReverseHolofoil":{"raw":0.32}},"tcgplayer":null,"cardmarket":null},"sv8pt5-94":{"scrydex":{"normal":{"raw":0.16},"reverseHolofoil":{"raw":0.22},"pokeBallReverseHolofoil":{"raw":0.36}},"tcgplayer":null,"cardmarket":null},"sv8pt5-93":{"scrydex":{"normal":{"raw":0.05},"reverseHolofoil":{"raw":0.19},"pokeBallReverseHolofoil":{"raw":0.26}},"tcgplayer":null,"cardmarket":null},"sv8pt5-92":{"scrydex":{"holofoil":{"raw":0.75,"psa10":29.07}},"tcgplayer":null,"cardmarket":null},"sv8pt5-91":{"scrydex":{"holofoil":{"raw":0.55,"psa10":58.42}},"tcgplayer":null,"cardmarket":null},"sv8pt5-90":{"scrydex":{"normal":{"raw":0.06,"psa10":44.99},"reverseHolofoil":{"raw":0.13,"psa10":44.99},"masterBallReverseHolofoil":{"raw":1.32,"psa10":65.51},"pokeBallReverseHolofoil":{"raw":0.33}},"tcgplayer":null,"cardmarket":null},"sv8pt5-89":{"scrydex":{"normal":{"raw":0.05,"psa10":37},"reverseHolofoil":{"raw":0.1,"psa10":39.99},"masterBallReverseHolofoil":{"raw":1.34,"psa10":94.99},"pokeBallReverseHolofoil":{"raw":0.34}},"tcgplayer":null,"cardmarket":null},"sv8pt5-88":{"scrydex":{"normal":{"raw":0.03},"reverseHolofoil":{"raw":0.08,"psa10":59.78},"masterBallReverseHolofoil":{"raw":7.29,"psa10":83.4},"pokeBallReverseHolofoil":{"raw":0.26}},"tcgplayer":null,"cardmarket":null},"sv8pt5-87":{"scrydex":{"normal":{"raw":0.07,"psa10":34.99},"reverseHolofoil":{"raw":0.13,"psa10":36.03},"masterBallReverseHolofoil":{"raw":6.83,"psa10":52.29},"pokeBallReverseHolofoil":{"raw":0.27}},"tcgplayer":null,"cardmarket":null},"sv8pt5-86":{"scrydex":{"normal":{"raw":0.2,"psa10":35},"reverseHolofoil":{"raw":0.21,"psa10":54.89},"masterBallReverseHolofoil":{"raw":1.73,"psa10":49.96},"playPokemonStamp":{"raw":0.13},"pokeBallReverseHolofoil":{"raw":0.35}},"tcgplayer":null,"cardmarket":null},"sv8pt5-85":{"scrydex":{"normal":{"raw":0.16,"psa10":41},"reverseHolofoil":{"raw":0.27,"psa10":13.5},"masterBallReverseHolofoil":{"raw":3.79,"psa10":47.48},"pokeBallReverseHolofoil":{"raw":0.41}},"tcgplayer":null,"cardmarket":null},"sv8pt5-84":{"scrydex":{"normal":{"raw":0.07},"reverseHolofoil":{"raw":0.13,"psa10":54.9},"masterBallReverseHolofoil":{"raw":6.76,"psa10":77.25},"pokeBallReverseHolofoil":{"raw":0.33}},"tcgplayer":null,"cardmarket":null},"sv8pt5-83":{"scrydex":{"normal":{"raw":0.06},"reverseHolofoil":{"raw":0.15,"psa10":26},"masterBallReverseHolofoil":{"raw":1.44,"psa10":64.4},"pokeBallReverseHolofoil":{"raw":0.34}},"tcgplayer":null,"cardmarket":null},"sv8pt5-82":{"scrydex":{"holofoil":{"raw":1.22,"psa10":124.91,"ace10":53.65},"expansionStamp":{"raw":7.33},"jumbo":{"raw":3.1}},"tcgplayer":null,"cardmarket":null},"sv8pt5-81":{"scrydex":{"normal":{"raw":0.07,"psa10":30},"reverseHolofoil":{"raw":0.12,"psa10":46},"masterBallReverseHolofoil":{"raw":1.6,"psa10":115.25},"pokeBallReverseHolofoil":{"raw":0.31}},"tcgplayer":null,"cardmarket":null},"sv8pt5-80":{"scrydex":{"holofoil":{"raw":0.18,"psa10":60.34},"reverseHolofoil":{"raw":0.18},"masterBallReverseHolofoil":{"raw":10.38,"psa10":13.09},"pokeBallReverseHolofoil":{"raw":0.58}},"tcgplayer":null,"cardmarket":null},"sv8pt5-79":{"scrydex":{"normal":{"raw":0.14},"reverseHolofoil":{"raw":0.18,"psa10":50},"masterBallReverseHolofoil":{"raw":1.52,"psa10":27.23},"pokeBallReverseHolofoil":{"raw":0.37}},"tcgplayer":null,"cardmarket":null},"sv8pt5-78":{"scrydex":{"holofoil":{"raw":0.23,"psa10":35.03},"reverseHolofoil":{"raw":0.21,"psa10":14.71},"masterBallReverseHolofoil":{"raw":8.63,"psa10":43.2},"pokeBallReverseHolofoil":{"raw":0.41}},"tcgplayer":null,"cardmarket":null},"sv8pt5-77":{"scrydex":{"normal":{"raw":0.14,"psa10":22.05},"reverseHolofoil":{"raw":0.22},"masterBallReverseHolofoil":{"raw":1.61,"psa10":65.83},"pokeBallReverseHolofoil":{"raw":0.35}},"tcgplayer":null,"cardmarket":null},"sv8pt5-76":{"scrydex":{"holofoil":{"raw":1.23,"psa10":81.92},"expansionStamp":{"raw":2.08}},"tcgplayer":null,"cardmarket":null},"sv8pt5-75":{"scrydex":{"holofoil":{"raw":5.36,"psa10":62.63,"ace10":50.3},"expansionStamp":{"raw":6.17,"psa10":70.44},"playPokemonStampHolofoil":{"raw":17.53}},"tcgplayer":null,"cardmarket":null},"sv8pt5-74":{"scrydex":{"normal":{"raw":0.21,"psa10":80.82,"ace10":26.76},"reverseHolofoil":{"raw":0.25,"psa10":79.27,"ace10":25.16},"masterBallReverseHolofoil":{"raw":10.22,"psa10":129.07},"pokeBallReverseHolofoil":{"raw":1.22},"pokemonDayStamp":{"raw":4.39}},"tcgplayer":null,"cardmarket":null},"sv8pt5-73":{"scrydex":{"holofoil":{"raw":1.15,"psa10":42},"jumbo":{"raw":3.63}},"tcgplayer":null,"cardmarket":null},"sv8pt5-72":{"scrydex":{"normal":{"raw":0.18},"reverseHolofoil":{"raw":0.2,"psa10":25.02},"masterBallReverseHolofoil":{"raw":2.69,"psa10":38.13},"pokeBallReverseHolofoil":{"raw":0.78}},"tcgplayer":null,"cardmarket":null},"sv8pt5-71":{"scrydex":{"normal":{"raw":0.19,"psa10":80},"reverseHolofoil":{"raw":0.18,"psa10":71.89},"masterBallReverseHolofoil":{"raw":3.35,"psa10":29.48},"pokeBallReverseHolofoil":{"raw":1.08}},"tcgplayer":null,"cardmarket":null},"sv8pt5-70":{"scrydex":{"holofoil":{"raw":0.05,"psa10":25.05},"reverseHolofoil":{"raw":0.11,"psa10":49.8},"masterBallReverseHolofoil":{"raw":4.66,"psa10":38.82},"pokeBallReverseHolofoil":{"raw":0.26}},"tcgplayer":null,"cardmarket":null},"sv8pt5-69":{"scrydex":{"normal":{"raw":0.05},"reverseHolofoil":{"raw":0.14,"psa10":21},"masterBallReverseHolofoil":{"raw":1.56,"psa10":36.85},"pokeBallReverseHolofoil":{"raw":0.26}},"tcgplayer":null,"cardmarket":null},"sv8pt5-68":{"scrydex":{"normal":{"raw":0.06},"reverseHolofoil":{"raw":0.13},"masterBallReverseHolofoil":{"raw":1.03,"psa10":52.11},"pokeBallReverseHolofoil":{"raw":0.22}},"tcgplayer":null,"cardmarket":null},"sv8pt5-67":{"scrydex":{"normal":{"raw":0.03},"reverseHolofoil":{"raw":0.1,"psa10":39.97},"masterBallReverseHolofoil":{"raw":5.06,"psa10":71.81},"pokeBallReverseHolofoil":{"raw":0.23}},"tcgplayer":null,"cardmarket":null},"sv8pt5-66":{"scrydex":{"normal":{"raw":0.04},"reverseHolofoil":{"raw":0.05},"masterBallReverseHolofoil":{"raw":1.04,"psa10":28.98},"pokeBallReverseHolofoil":{"raw":0.27}},"tcgplayer":null,"cardmarket":null},"sv8pt5-65":{"scrydex":{"holofoil":{"raw":0.12,"psa10":62.23},"reverseHolofoil":{"raw":0.15,"psa10":58.77},"masterBallReverseHolofoil":{"raw":6.21,"psa10":80.03},"pokeBallReverseHolofoil":{"raw":0.39}},"tcgplayer":null,"cardmarket":null},"sv8pt5-64":{"scrydex":{"holofoil":{"raw":0.63,"psa10":50.21},"expansionStamp":{"raw":0.75,"psa10":34.55}},"tcgplayer":null,"cardmarket":null},"sv8pt5-63":{"scrydex":{"normal":{"raw":0.07,"psa10":174.79},"reverseHolofoil":{"raw":0.16,"psa10":23.02},"masterBallReverseHolofoil":{"raw":8.01,"psa10":124.51},"pokeBallReverseHolofoil":{"raw":0.36}},"tcgplayer":null,"cardmarket":null},"sv8pt5-62":{"scrydex":{"normal":{"raw":0.06,"psa10":44.46},"reverseHolofoil":{"raw":0.15,"psa10":39.99},"masterBallReverseHolofoil":{"raw":1.27,"psa10":51.35},"pokeBallReverseHolofoil":{"raw":0.25}},"tcgplayer":null,"cardmarket":null},"sv8pt5-61":{"scrydex":{"normal":{"raw":0.04,"psa10":59.83},"reverseHolofoil":{"raw":0.1,"psa10":31.06},"masterBallReverseHolofoil":{"raw":1.23,"psa10":38.35},"pokeBallReverseHolofoil":{"raw":0.19}},"tcgplayer":null,"cardmarket":null},"sv8pt5-60":{"scrydex":{"holofoil":{"raw":5.18,"psa10":306.76,"ace10":67.36},"expansionStamp":{"raw":18.69,"psa10":99.4},"playPokemonStampHolofoil":{"raw":57.08}},"tcgplayer":null,"cardmarket":null},"sv8pt5-59":{"scrydex":{"holofoil":{"raw":0.31,"psa10":146.46,"ace10":187.53},"reverseHolofoil":{"raw":0.38,"psa10":105.79},"cosmosHolofoil":{"raw":10.98},"masterBallReverseHolofoil":{"raw":55.55,"psa10":413.83},"pokeBallReverseHolofoil":{"raw":2.6}},"tcgplayer":null,"cardmarket":null},"sv8pt5-58":{"scrydex":{"holofoil":{"raw":1.02,"psa10":48.26}},"tcgplayer":null,"cardmarket":null},"sv8pt5-57":{"scrydex":{"holofoil":{"raw":0.08,"psa10":11},"reverseHolofoil":{"raw":0.2,"psa10":27.8},"masterBallReverseHolofoil":{"raw":5.69,"psa10":122.64},"pokeBallReverseHolofoil":{"raw":0.32}},"tcgplayer":null,"cardmarket":null},"sv8pt5-56":{"scrydex":{"holofoil":{"raw":0.56,"psa10":38.01}},"tcgplayer":null,"cardmarket":null},"sv8pt5-55":{"scrydex":{"normal":{"raw":0.05,"psa10":34.01},"reverseHolofoil":{"raw":0.17,"psa10":9},"masterBallReverseHolofoil":{"raw":5.88,"psa10":49.51},"pokeBallReverseHolofoil":{"raw":0.31}},"tcgplayer":null,"cardmarket":null},"sv8pt5-54":{"scrydex":{"holofoil":{"raw":0.09,"psa10":49.79},"reverseHolofoil":{"raw":0.14,"psa10":50},"masterBallReverseHolofoil":{"raw":8.03,"psa10":45.74},"pokeBallReverseHolofoil":{"raw":0.36}},"tcgplayer":null,"cardmarket":null},"sv8pt5-53":{"scrydex":{"normal":{"raw":0.04},"reverseHolofoil":{"raw":0.1},"masterBallReverseHolofoil":{"raw":5.34,"psa10":10.07},"pokeBallReverseHolofoil":{"raw":0.23}},"tcgplayer":null,"cardmarket":null},"sv8pt5-52":{"scrydex":{"normal":{"raw":0.06,"psa10":23.5},"reverseHolofoil":{"raw":0.06},"masterBallReverseHolofoil":{"raw":1.09,"psa10":39.87},"pokeBallReverseHolofoil":{"raw":0.26}},"tcgplayer":null,"cardmarket":null},"sv8pt5-51":{"scrydex":{"holofoil":{"raw":0.73,"psa10":45.82},"expansionStamp":{"raw":0.98,"psa10":54.9}},"tcgplayer":null,"cardmarket":null},"sv8pt5-50":{"scrydex":{"normal":{"raw":0.11,"psa10":59.99},"reverseHolofoil":{"raw":0.15,"psa10":54.59},"masterBallReverseHolofoil":{"raw":11.11,"psa10":74.86},"pokeBallReverseHolofoil":{"raw":0.39}},"tcgplayer":null,"cardmarket":null},"sv8pt5-49":{"scrydex":{"holofoil":{"raw":0.17,"psa10":49.88},"reverseHolofoil":{"raw":0.18,"psa10":60.85},"masterBallReverseHolofoil":{"raw":8.82,"psa10":76.54},"pokeBallReverseHolofoil":{"raw":0.31}},"tcgplayer":null,"cardmarket":null},"sv8pt5-48":{"scrydex":{"normal":{"raw":0.03},"reverseHolofoil":{"raw":0.09,"psa10":26.13},"masterBallReverseHolofoil":{"raw":7.31,"psa10":20.64},"pokeBallReverseHolofoil":{"raw":0.34}},"tcgplayer":null,"cardmarket":null},"sv8pt5-47":{"scrydex":{"normal":{"raw":0.05,"psa10":109.92},"reverseHolofoil":{"raw":0.08,"psa10":40},"masterBallReverseHolofoil":{"raw":2.2,"psa10":87.8},"pokeBallReverseHolofoil":{"raw":0.35}},"tcgplayer":null,"cardmarket":null},"sv8pt5-46":{"scrydex":{"holofoil":{"raw":0.08,"psa10":10},"reverseHolofoil":{"raw":0.15,"psa10":40},"masterBallReverseHolofoil":{"raw":4.76,"psa10":25.97},"pokeBallReverseHolofoil":{"raw":0.25}},"tcgplayer":null,"cardmarket":null},"sv8pt5-45":{"scrydex":{"holofoil":{"raw":0.08,"psa10":8.99},"reverseHolofoil":{"raw":0.11},"masterBallReverseHolofoil":{"raw":6.49,"psa10":43.75},"pokeBallReverseHolofoil":{"raw":0.28}},"tcgplayer":null,"cardmarket":null},"sv8pt5-44":{"scrydex":{"holofoil":{"raw":0.29,"psa10":20},"reverseHolofoil":{"raw":0.39},"masterBallReverseHolofoil":{"raw":10.53,"psa10":79.23},"pokeBallReverseHolofoil":{"raw":0.86}},"tcgplayer":null,"cardmarket":null},"sv8pt5-43":{"scrydex":{"holofoil":{"raw":0.07,"psa10":49.99},"reverseHolofoil":{"raw":0.12,"psa10":25},"masterBallReverseHolofoil":{"raw":11.88,"psa10":31.4},"pokeBallReverseHolofoil":{"raw":0.35}},"tcgplayer":null,"cardmarket":null},"sv8pt5-42":{"scrydex":{"normal":{"raw":0.07,"psa10":58.75},"reverseHolofoil":{"raw":0.12,"psa10":35.05},"masterBallReverseHolofoil":{"raw":6.26,"psa10":59.77},"pokeBallReverseHolofoil":{"raw":0.28}},"tcgplayer":null,"cardmarket":null},"sv8pt5-41":{"scrydex":{"holofoil":{"raw":2.24,"psa10":59.2,"ace10":26.43},"expansionStamp":{"raw":7.03,"psa10":49.1}},"tcgplayer":null,"cardmarket":null},"sv8pt5-40":{"scrydex":{"holofoil":{"raw":0.29,"psa10":53.44},"reverseHolofoil":{"raw":0.36,"psa10":67.01},"cosmosHolofoil":{"raw":2.69},"masterBallReverseHolofoil":{"raw":27.57,"psa10":140.71},"pokeBallReverseHolofoil":{"raw":1.59},"pokemonDayStamp":{"raw":7.25}},"tcgplayer":null,"cardmarket":null},"sv8pt5-39":{"scrydex":{"normal":{"raw":0.05},"reverseHolofoil":{"raw":0.18,"psa10":13},"masterBallReverseHolofoil":{"raw":6.42,"psa10":32.42},"pokeBallReverseHolofoil":{"raw":0.32}},"tcgplayer":null,"cardmarket":null},"sv8pt5-38":{"scrydex":{"normal":{"raw":0.07,"psa10":69.95},"reverseHolofoil":{"raw":0.07},"masterBallReverseHolofoil":{"raw":1.17,"psa10":21},"pokeBallReverseHolofoil":{"raw":0.33}},"tcgplayer":null,"cardmarket":null},"sv8pt5-37":{"scrydex":{"holofoil":{"raw":0.26,"psa10":149.58},"reverseHolofoil":{"raw":0.27,"psa10":40},"masterBallReverseHolofoil":{"raw":10.1,"psa10":34.11},"pokeBallReverseHolofoil":{"raw":0.46}},"tcgplayer":null,"cardmarket":null},"sv8pt5-36":{"scrydex":{"normal":{"raw":0.23,"psa10":46},"reverseHolofoil":{"raw":0.25,"psa10":23},"masterBallReverseHolofoil":{"raw":1.94,"psa10":46.24},"pokeBallReverseHolofoil":{"raw":0.5}},"tcgplayer":null,"cardmarket":null},"sv8pt5-35":{"scrydex":{"normal":{"raw":0.18,"psa10":50},"reverseHolofoil":{"raw":0.17,"psa10":13},"masterBallReverseHolofoil":{"raw":1.92,"psa10":66.3},"pokeBallReverseHolofoil":{"raw":0.64}},"tcgplayer":null,"cardmarket":null},"sv8pt5-34":{"scrydex":{"holofoil":{"raw":2.63,"psa10":52.09},"expansionStamp":{"raw":5.88,"psa10":58.54},"playPokemonStampHolofoil":{"raw":13.79}},"tcgplayer":null,"cardmarket":null},"sv8pt5-33":{"scrydex":{"holofoil":{"raw":0.32,"psa10":116.23},"reverseHolofoil":{"raw":0.27,"psa10":56.04},"cosmosHolofoil":{"raw":2.11},"masterBallReverseHolofoil":{"raw":20.69,"psa10":200.82,"ace10":113.53},"pokeBallReverseHolofoil":{"raw":1.22}},"tcgplayer":null,"cardmarket":null},"sv8pt5-32":{"scrydex":{"holofoil":{"raw":0.62,"psa10":22.51}},"tcgplayer":null,"cardmarket":null},"sv8pt5-31":{"scrydex":{"holofoil":{"raw":0.62,"psa10":36.45,"ace10":23.13}},"tcgplayer":null,"cardmarket":null},"sv8pt5-30":{"scrydex":{"holofoil":{"raw":3.11,"psa10":45.48,"ace10":42.43},"expansionStamp":{"raw":5.11,"psa10":57.14},"playPokemonStampHolofoil":{"raw":14.45}},"tcgplayer":null,"cardmarket":null},"sv8pt5-29":{"scrydex":{"holofoil":{"raw":0.26,"psa10":152.19,"ace10":31.43},"reverseHolofoil":{"raw":0.29,"psa10":40.7},"cosmosHolofoil":{"raw":1.32},"masterBallReverseHolofoil":{"raw":21.25,"psa10":214},"pokeBallReverseHolofoil":{"raw":1.15}},"tcgplayer":null,"cardmarket":null},"sv8pt5-28":{"scrydex":{"holofoil":{"raw":2.12,"psa10":117.38}},"tcgplayer":null,"cardmarket":null},"sv8pt5-27":{"scrydex":{"holofoil":{"raw":0.89,"psa10":43.01}},"tcgplayer":null,"cardmarket":null},"sv8pt5-26":{"scrydex":{"holofoil":{"raw":1.99,"psa10":50.96,"ace10":44.65},"expansionStamp":{"raw":4.54,"psa10":44.89},"holidayStamp":{"raw":1.78},"playPokemonStampHolofoil":{"raw":13.85}},"tcgplayer":null,"cardmarket":null},"sv8pt5-25":{"scrydex":{"holofoil":{"raw":0.28,"psa10":209.21,"ace10":227.91},"reverseHolofoil":{"raw":0.27,"psa10":49.99},"masterBallReverseHolofoil":{"raw":18.61,"psa10":240.91},"pokeBallReverseHolofoil":{"raw":0.93}},"tcgplayer":null,"cardmarket":null},"sv8pt5-24":{"scrydex":{"normal":{"raw":0.15,"psa10":49.91,"ace10":30.36},"reverseHolofoil":{"raw":0.2,"psa10":46.23},"masterBallReverseHolofoil":{"raw":11.09,"psa10":108.51},"pokeBallReverseHolofoil":{"raw":0.46}},"tcgplayer":null,"cardmarket":null},"sv8pt5-23":{"scrydex":{"holofoil":{"raw":2.75,"psa10":47.33,"ace10":56.41},"expansionStamp":{"raw":5.54,"psa10":62.71},"playPokemonStampHolofoil":{"raw":12.32}},"tcgplayer":null,"cardmarket":null},"sv8pt5-22":{"scrydex":{"holofoil":{"raw":0.22,"psa10":312.57},"reverseHolofoil":{"raw":0.21,"psa10":33.39},"cosmosHolofoil":{"raw":0.69},"masterBallReverseHolofoil":{"raw":19.7,"psa10":341.9},"pokeBallReverseHolofoil":{"raw":1.16}},"tcgplayer":null,"cardmarket":null},"sv8pt5-21":{"scrydex":{"normal":{"raw":0.12},"reverseHolofoil":{"raw":0.21,"psa10":29.92},"masterBallReverseHolofoil":{"raw":1.75,"psa10":44.96},"pokeBallReverseHolofoil":{"raw":0.34}},"tcgplayer":null,"cardmarket":null},"sv8pt5-20":{"scrydex":{"normal":{"raw":0.12},"reverseHolofoil":{"raw":0.17,"psa10":39.81},"masterBallReverseHolofoil":{"raw":1.66,"psa10":44.95},"pokeBallReverseHolofoil":{"raw":0.34}},"tcgplayer":null,"cardmarket":null},"sv8pt5-19":{"scrydex":{"normal":{"raw":0.07,"psa10":70.51},"reverseHolofoil":{"raw":0.13,"psa10":48.23},"masterBallReverseHolofoil":{"raw":1.62,"psa10":66.78},"pokeBallReverseHolofoil":{"raw":0.35}},"tcgplayer":null,"cardmarket":null},"sv8pt5-18":{"scrydex":{"normal":{"raw":0.11,"psa10":90.94},"reverseHolofoil":{"raw":0.12,"psa10":102.46},"masterBallReverseHolofoil":{"raw":3.15,"psa10":93.93},"pokeBallReverseHolofoil":{"raw":0.47}},"tcgplayer":null,"cardmarket":null},"sv8pt5-17":{"scrydex":{"holofoil":{"raw":0.62,"psa10":29.49}},"tcgplayer":null,"cardmarket":null},"sv8pt5-16":{"scrydex":{"normal":{"raw":0.04},"reverseHolofoil":{"raw":0.1,"psa10":39.91},"masterBallReverseHolofoil":{"raw":1.11,"psa10":36.69},"pokeBallReverseHolofoil":{"raw":0.28}},"tcgplayer":null,"cardmarket":null},"sv8pt5-15":{"scrydex":{"normal":{"raw":0.07},"reverseHolofoil":{"raw":0.17,"psa10":38.92},"masterBallReverseHolofoil":{"raw":1.24,"psa10":39.05},"pokeBallReverseHolofoil":{"raw":0.25}},"tcgplayer":null,"cardmarket":null},"sv8pt5-14":{"scrydex":{"holofoil":{"raw":4.1,"psa10":43.64,"ace10":34.54},"expansionStamp":{"raw":5.94,"psa10":62.29},"playPokemonStampHolofoil":{"raw":16.59}},"tcgplayer":null,"cardmarket":null},"sv8pt5-13":{"scrydex":{"holofoil":{"raw":0.26,"psa10":160.31,"ace10":24.04},"reverseHolofoil":{"raw":0.33,"psa10":46.01},"cosmosHolofoil":{"raw":0.89},"masterBallReverseHolofoil":{"raw":24.82,"psa10":134.99},"pokeBallReverseHolofoil":{"raw":1.07}},"tcgplayer":null,"cardmarket":null},"sv8pt5-12":{"scrydex":{"holofoil":{"raw":4.13,"psa10":107.31}},"tcgplayer":null,"cardmarket":null},"sv8pt5-11":{"scrydex":{"holofoil":{"raw":0.63,"psa10":28.95}},"tcgplayer":null,"cardmarket":null},"sv8pt5-10":{"scrydex":{"normal":{"raw":0.12},"reverseHolofoil":{"raw":0.2},"masterBallReverseHolofoil":{"raw":1.66,"psa10":77.95},"pokeBallReverseHolofoil":{"raw":0.33}},"tcgplayer":null,"cardmarket":null},"sv8pt5-9":{"scrydex":{"normal":{"raw":0.1,"psa10":550},"reverseHolofoil":{"raw":0.22,"psa10":18.45},"masterBallReverseHolofoil":{"raw":2.19,"psa10":84.26},"pokeBallReverseHolofoil":{"raw":0.35}},"tcgplayer":null,"cardmarket":null},"sv8pt5-8":{"scrydex":{"holofoil":{"raw":0.07,"psa10":39.64},"reverseHolofoil":{"raw":0.15,"psa10":17},"masterBallReverseHolofoil":{"raw":10.7,"psa10":76.37},"pokeBallReverseHolofoil":{"raw":0.28}},"tcgplayer":null,"cardmarket":null},"sv8pt5-7":{"scrydex":{"normal":{"raw":0.06},"reverseHolofoil":{"raw":0.08,"psa10":39.81},"masterBallReverseHolofoil":{"raw":1.29,"psa10":38.3},"pokeBallReverseHolofoil":{"raw":0.32}},"tcgplayer":null,"cardmarket":null},"sv8pt5-6":{"scrydex":{"holofoil":{"raw":3.96,"psa10":60.33},"expansionStamp":{"raw":5.44,"psa10":73.01,"ace10":49.63},"playPokemonStampHolofoil":{"raw":17.17}},"tcgplayer":null,"cardmarket":null},"sv8pt5-5":{"scrydex":{"holofoil":{"raw":0.31,"psa10":144.22},"reverseHolofoil":{"raw":0.31,"psa10":74.87},"cosmosHolofoil":{"raw":1.42},"masterBallReverseHolofoil":{"raw":24.49,"psa10":112.86},"pokeBallReverseHolofoil":{"raw":1.54}},"tcgplayer":null,"cardmarket":null},"sv8pt5-4":{"scrydex":{"normal":{"raw":0.2,"psa10":35},"reverseHolofoil":{"raw":0.22,"psa10":61.59},"masterBallReverseHolofoil":{"raw":3.79,"psa10":50.65},"playPokemonStamp":{"raw":0.2},"pokeBallReverseHolofoil":{"raw":0.7}},"tcgplayer":null,"cardmarket":null},"sv8pt5-3":{"scrydex":{"normal":{"raw":0.05},"reverseHolofoil":{"raw":0.08,"psa10":59.69},"masterBallReverseHolofoil":{"raw":1.45,"psa10":80.67},"pokeBallReverseHolofoil":{"raw":0.29}},"tcgplayer":null,"cardmarket":null},"sv8pt5-2":{"scrydex":{"normal":{"raw":0.03,"psa10":41},"reverseHolofoil":{"raw":0.11},"masterBallReverseHolofoil":{"raw":9.72},"pokeBallReverseHolofoil":{"raw":0.26}},"tcgplayer":null,"cardmarket":null},"sv8pt5-1":{"scrydex":{"normal":{"raw":0.05},"reverseHolofoil":{"raw":0.06,"psa10":84.83},"masterBallReverseHolofoil":{"raw":1.32,"psa10":49.37},"pokeBallReverseHolofoil":{"raw":0.3}},"tcgplayer":null,"cardmarket":null}}