{"ex2-1":{"variant":"holofoil","grade":"raw","current":17.33,"daily":{"changePct":0.7558139534883663,"direction":"flat"},"weekly":{"changePct":-0.0868055555555383,"direction":"flat"},"monthly":{"changePct":-0.4382810392879265,"direction":"flat"},"allVariants":{"holofoil":{"raw":{"current":17.33,"daily":{"changePct":0.7558139534883663,"direction":"flat"},"weekly":{"changePct":-0.0868055555555383,"direction":"flat"},"monthly":{"changePct":-0.4382810392879265,"direction":"flat"}},"psa10":{"current":210.89,"daily":{"changePct":0,"direction":"flat"},"weekly":{"changePct":2.6954060818819305e-14,"direction":"flat"},"monthly":{"changePct":0,"direction":"flat"}}},"reverseHolofoil":{"raw":{"current":13.76,"daily":{"changePct":0,"direction":"flat"},"weekly":{"changePct":6.36042402826853,"direction":"up"},"monthly":{"changePct":11.839657029694383,"direction":"up"}}},"prereleaseStamp":{"raw":{"current":77.25,"daily":{"changePct":0,"direction":"flat"},"weekly":{"changePct":0,"direction":"flat"},"monthly":{"changePct":0.2654867256637151,"direction":"flat"}}}}},"ex2-10":{"variant":"holofoil","grade":"raw","current":79.72,"daily":{"changePct":0,"direction":"flat"},"weekly":{"changePct":0,"direction":"flat"},"monthly":{"changePct":3.971923833914322,"direction":"up"},"allVariants":{"holofoil":{"raw":{"current":79.72,"daily":{"changePct":0,"direction":"flat"},"weekly":{"changePct":0,"direction":"flat"},"monthly":{"changePct":3.971923833914322,"direction":"up"}},"psa10":{"current":1925.48,"daily":{"changePct":0,"direction":"flat"},"weekly":{"changePct":-2.361735000552922e-14,"direction":"flat"},"monthly":{"changePct":-3.542602500829383e-14,"direction":"flat"}}},"reverseHolofoil":{"raw":{"current":42.11,"daily":{"changePct":0,"direction":"flat"},"weekly":{"changePct":0,"direction":"flat"},"monthly":{"changePct":2.8190273245877107,"direction":"up"}}}}},"ex2-100":{"variant":"holofoil","grade":"raw","current":118.17,"daily":{"changePct":0,"direction":"flat"},"weekly":{"changePct":1.2025771951596856e-14,"direction":"flat"},"monthly":{"changePct":0.184975375153147,"direction":"flat"},"allVariants":{"holofoil":{"raw":{"current":118.17,"daily":{"changePct":0,"direction":"flat"},"weekly":{"changePct":1.2025771951596856e-14,"direction":"flat"},"monthly":{"changePct":0.184975375153147,"direction":"flat"}},"psa10":{"current":2370.89,"daily":{"changePct":0,"direction":"flat"},"weekly":{"changePct":66.34572690050565,"direction":"up"},"monthly":{"changePct":165.06965599931357,"direction":"up"}}}}},"ex2-11":{"variant":"holofoil","grade":"raw","current":32.49,"daily":{"changePct":0,"direction":"flat"},"weekly":{"changePct":-1.6263679224879868,"direction":"down"},"monthly":{"changePct":-1.2998751775491677,"direction":"down"},"allVariants":{"holofoil":{"raw":{"current":32.49,"daily":{"changePct":0,"direction":"flat"},"weekly":{"changePct":-1.6263679224879868,"direction":"down"},"monthly":{"changePct":-1.2998751775491677,"direction":"down"}},"psa10":{"current":250.62,"daily":{"changePct":0,"direction":"flat"},"weekly":{"changePct":-4.33829543595615,"direction":"down"},"monthly":{"changePct":-8.20214641388057,"direction":"down"}}},"reverseHolofoil":{"raw":{"current":12.61,"daily":{"changePct":0,"direction":"flat"},"weekly":{"changePct":0,"direction":"flat"},"monthly":{"changePct":0,"direction":"flat"}},"psa10":{"current":475,"daily":{"changePct":0,"direction":"flat"},"weekly":{"changePct":0,"direction":"flat"},"monthly":{"changePct":0,"direction":"flat"}}}}},"ex2-12":{"variant":"holofoil","grade":"raw","current":26.15,"daily":{"changePct":0,"direction":"flat"},"weekly":{"changePct":0.2409506598762436,"direction":"flat"},"monthly":{"changePct":7.798396260800544,"direction":"up"},"allVariants":{"holofoil":{"raw":{"current":26.15,"daily":{"changePct":0,"direction":"flat"},"weekly":{"changePct":0.2409506598762436,"direction":"flat"},"monthly":{"changePct":7.798396260800544,"direction":"up"}},"psa10":{"current":99.14,"daily":{"changePct":-1.4334128217875732e-14,"direction":"flat"},"weekly":{"changePct":0,"direction":"flat"},"monthly":{"changePct":-2.8668256435751464e-14,"direction":"flat"}}},"reverseHolofoil":{"raw":{"current":14.47,"daily":{"changePct":1.22761357249499e-14,"direction":"flat"},"weekly":{"changePct":2.468386444107209,"direction":"up"},"monthly":{"changePct":3.143681715110295,"direction":"up"}}}}},"ex2-13":{"variant":"holofoil","grade":"raw","current":21.36,"daily":{"changePct":0,"direction":"flat"},"weekly":{"changePct":1.6632554676032312e-14,"direction":"flat"},"monthly":{"changePct":-0.6259516156318656,"direction":"flat"},"allVariants":{"holofoil":{"raw":{"current":21.36,"daily":{"changePct":0,"direction":"flat"},"weekly":{"changePct":1.6632554676032312e-14,"direction":"flat"},"monthly":{"changePct":-0.6259516156318656,"direction":"flat"}},"psa10":{"current":99.18,"daily":{"changePct":-1.4328347161929827e-14,"direction":"flat"},"weekly":{"changePct":-1.4328347161929827e-14,"direction":"flat"},"monthly":{"changePct":null,"direction":"flat"}}},"reverseHolofoil":{"raw":{"current":21.74,"daily":{"changePct":8.808808808808799,"direction":"up"},"weekly":{"changePct":4.404404404404399,"direction":"up"},"monthly":{"changePct":3.6349605503000317,"direction":"up"}},"psa10":{"current":55,"daily":{"changePct":0,"direction":"flat"},"weekly":{"changePct":0,"direction":"flat"},"monthly":{"changePct":null,"direction":"flat"}}}}},"ex2-14":{"variant":"holofoil","grade":"raw","current":38.75,"daily":{"changePct":0,"direction":"flat"},"weekly":{"changePct":0.697924787467067,"direction":"flat"},"monthly":{"changePct":0.7573549843107275,"direction":"flat"},"allVariants":{"holofoil":{"raw":{"current":38.75,"daily":{"changePct":0,"direction":"flat"},"weekly":{"changePct":0.697924787467067,"direction":"flat"},"monthly":{"changePct":0.7573549843107275,"direction":"flat"}},"psa10":{"current":199.82,"daily":{"changePct":0,"direction":"flat"},"weekly":{"changePct":-1.422365600560705e-14,"direction":"flat"},"monthly":{"changePct":-2.84473120112141e-14,"direction":"flat"}}},"reverseHolofoil":{"raw":{"current":26.16,"daily":{"changePct":0,"direction":"flat"},"weekly":{"changePct":0,"direction":"flat"},"monthly":{"changePct":-7.644906605045283,"direction":"down"}},"psa10":{"current":445,"daily":{"changePct":0,"direction":"flat"},"weekly":{"changePct":-1.277380199119281e-14,"direction":"flat"},"monthly":{"changePct":-1.277380199119281e-14,"direction":"flat"}}}}},"ex2-15":{"variant":"normal","grade":"raw","current":7.67,"daily":{"changePct":0.656167979002634,"direction":"flat"},"weekly":{"changePct":1.3157894736842213,"direction":"up"},"monthly":{"changePct":4.012301784825416,"direction":"up"},"allVariants":{"normal":{"raw":{"current":7.67,"daily":{"changePct":0.656167979002634,"direction":"flat"},"weekly":{"changePct":1.3157894736842213,"direction":"up"},"monthly":{"changePct":4.012301784825416,"direction":"up"}},"psa10":{"current":100.75,"daily":{"changePct":0,"direction":"flat"},"weekly":{"changePct":-55.42288997465378,"direction":"down"},"monthly":{"changePct":-22.330617968943656,"direction":"down"}}},"reverseHolofoil":{"raw":{"current":158.15,"daily":{"changePct":0,"direction":"flat"},"weekly":{"changePct":1.7971362270252297e-14,"direction":"flat"},"monthly":{"changePct":0,"direction":"flat"}},"psa10":{"current":475,"daily":{"changePct":0,"direction":"flat"},"weekly":{"changePct":0,"direction":"flat"},"monthly":{"changePct":0,"direction":"flat"}}}}},"ex2-16":{"variant":"normal","grade":"raw","current":12.71,"daily":{"changePct":0,"direction":"flat"},"weekly":{"changePct":0.9989783176297161,"direction":"flat"},"monthly":{"changePct":0.05354697202172281,"direction":"flat"},"allVariants":{"normal":{"raw":{"current":12.71,"daily":{"changePct":0,"direction":"flat"},"weekly":{"changePct":0.9989783176297161,"direction":"flat"},"monthly":{"changePct":0.05354697202172281,"direction":"flat"}},"psa10":{"current":179.35,"daily":{"changePct":0,"direction":"flat"},"weekly":{"changePct":0,"direction":"flat"},"monthly":{"changePct":-1.5847064081630334e-14,"direction":"flat"}}},"reverseHolofoil":{"raw":{"current":84.98,"daily":{"changePct":1.6722587332551195e-14,"direction":"flat"},"weekly":{"changePct":0,"direction":"flat"},"monthly":{"changePct":3.3445174665102396e-14,"direction":"flat"}},"psa10":{"current":2926.98,"daily":{"changePct":1.5536401030634448e-14,"direction":"flat"},"weekly":{"changePct":99.58094436554276,"direction":"up"},"monthly":{"changePct":491.7229437229436,"direction":"up"}}},"nonEreader":{"raw":{"current":6.59,"daily":{"changePct":2.968749999999992,"direction":"up"},"weekly":{"changePct":1.484374999999996,"direction":"up"},"monthly":{"changePct":0.8538822090890505,"direction":"flat"}}}}},"ex2-17":{"variant":"normal","grade":"raw","current":2.27,"daily":{"changePct":-1.731601731601733,"direction":"down"},"weekly":{"changePct":-0.8658008658008474,"direction":"flat"},"monthly":{"changePct":-0.24737167594308826,"direction":"flat"},"allVariants":{"normal":{"raw":{"current":2.27,"daily":{"changePct":-1.731601731601733,"direction":"down"},"weekly":{"changePct":-0.8658008658008474,"direction":"flat"},"monthly":{"changePct":-0.24737167594308826,"direction":"flat"}}},"reverseHolofoil":{"raw":{"current":19.94,"daily":{"changePct":0,"direction":"flat"},"weekly":{"changePct":1.7817019452359586e-14,"direction":"flat"},"monthly":{"changePct":0,"direction":"flat"}},"psa10":{"current":179,"daily":{"changePct":1.587804996111956e-14,"direction":"flat"},"weekly":{"changePct":3.1756099922239125e-14,"direction":"flat"},"monthly":{"changePct":1.5878049961119563e-14,"direction":"flat"}}}}},"ex2-18":{"variant":"normal","grade":"raw","current":1.51,"daily":{"changePct":2.027027027027029,"direction":"up"},"weekly":{"changePct":1.0135135135135371,"direction":"up"},"monthly":{"changePct":-1.4061421670117031,"direction":"down"},"allVariants":{"normal":{"raw":{"current":1.51,"daily":{"changePct":2.027027027027029,"direction":"up"},"weekly":{"changePct":1.0135135135135371,"direction":"up"},"monthly":{"changePct":-1.4061421670117031,"direction":"down"}}},"reverseHolofoil":{"raw":{"current":12.32,"daily":{"changePct":0,"direction":"flat"},"weekly":{"changePct":0,"direction":"flat"},"monthly":{"changePct":1.4418480839287746e-14,"direction":"flat"}},"psa10":{"current":195,"daily":{"changePct":0,"direction":"flat"},"weekly":{"changePct":-2.915047121067077e-14,"direction":"flat"},"monthly":{"changePct":-2.915047121067077e-14,"direction":"flat"}}}}},"ex2-19":{"variant":"normal","grade":"raw","current":1.51,"daily":{"changePct":-6.211180124223608,"direction":"down"},"weekly":{"changePct":-0.27397260273973634,"direction":"flat"},"monthly":{"changePct":2.5573714963163576,"direction":"up"},"allVariants":{"normal":{"raw":{"current":1.51,"daily":{"changePct":-6.211180124223608,"direction":"down"},"weekly":{"changePct":-0.27397260273973634,"direction":"flat"},"monthly":{"changePct":2.5573714963163576,"direction":"up"}},"psa10":{"current":26.08,"daily":{"changePct":0,"direction":"flat"},"weekly":{"changePct":0,"direction":"flat"},"monthly":{"changePct":-2.724473680061734e-14,"direction":"flat"}}},"reverseHolofoil":{"raw":{"current":9.74,"daily":{"changePct":0,"direction":"flat"},"weekly":{"changePct":-1.8237749891173e-14,"direction":"flat"},"monthly":{"changePct":-1.8237749891173e-14,"direction":"flat"}}}}},"ex2-2":{"variant":"holofoil","grade":"raw","current":18.39,"daily":{"changePct":0,"direction":"flat"},"weekly":{"changePct":-1.9318725822732465e-14,"direction":"flat"},"monthly":{"changePct":1.9318725822732468e-14,"direction":"flat"},"allVariants":{"holofoil":{"raw":{"current":18.39,"daily":{"changePct":0,"direction":"flat"},"weekly":{"changePct":-1.9318725822732465e-14,"direction":"flat"},"monthly":{"changePct":1.9318725822732468e-14,"direction":"flat"}},"psa10":{"current":590.7,"daily":{"changePct":0,"direction":"flat"},"weekly":{"changePct":0,"direction":"flat"},"monthly":{"changePct":0,"direction":"flat"}}},"reverseHolofoil":{"raw":{"current":19.97,"daily":{"changePct":0,"direction":"flat"},"weekly":{"changePct":-1.77902537746645e-14,"direction":"flat"},"monthly":{"changePct":0,"direction":"flat"}},"psa10":{"current":655,"daily":{"changePct":0,"direction":"flat"},"weekly":{"changePct":-1.735676911780397e-14,"direction":"flat"},"monthly":{"changePct":0,"direction":"flat"}}}}},"ex2-20":{"variant":"normal","grade":"raw","current":7,"daily":{"changePct":-0.8498583569405045,"direction":"flat"},"weekly":{"changePct":-0.9859154929577383,"direction":"flat"},"monthly":{"changePct":0.15432098765431884,"direction":"flat"},"allVariants":{"normal":{"raw":{"current":7,"daily":{"changePct":-0.8498583569405045,"direction":"flat"},"weekly":{"changePct":-0.9859154929577383,"direction":"flat"},"monthly":{"changePct":0.15432098765431884,"direction":"flat"}},"psa10":{"current":96.94,"daily":{"changePct":0,"direction":"flat"},"weekly":{"changePct":-1.4659433376523624e-14,"direction":"flat"},"monthly":{"changePct":1.465943337652363e-14,"direction":"flat"}}},"reverseHolofoil":{"raw":{"current":33.06,"daily":{"changePct":0,"direction":"flat"},"weekly":{"changePct":2.1492520742894743e-14,"direction":"flat"},"monthly":{"changePct":2.1492520742894743e-14,"direction":"flat"}},"psa10":{"current":750,"daily":{"changePct":0,"direction":"flat"},"weekly":{"changePct":0,"direction":"flat"},"monthly":{"changePct":0,"direction":"flat"}}}}},"ex2-21":{"variant":"normal","grade":"raw","current":1.54,"daily":{"changePct":0,"direction":"flat"},"weekly":{"changePct":3.355704697986565,"direction":"up"},"monthly":{"changePct":23.552409129332204,"direction":"up"},"allVariants":{"normal":{"raw":{"current":1.54,"daily":{"changePct":0,"direction":"flat"},"weekly":{"changePct":3.355704697986565,"direction":"up"},"monthly":{"changePct":23.552409129332204,"direction":"up"}},"psa10":{"current":130,"daily":{"changePct":0,"direction":"flat"},"weekly":{"changePct":-2.1862853408003078e-14,"direction":"flat"},"monthly":{"changePct":-2.1862853408003078e-14,"direction":"flat"}}},"reverseHolofoil":{"raw":{"current":7.49,"daily":{"changePct":1.185818984913385e-14,"direction":"flat"},"weekly":{"changePct":-1.1858189849133847e-14,"direction":"flat"},"monthly":{"changePct":-1.1858189849133847e-14,"direction":"flat"}}}}},"ex2-22":{"variant":"normal","grade":"raw","current":1.34,"daily":{"changePct":0,"direction":"flat"},"weekly":{"changePct":0,"direction":"flat"},"monthly":{"changePct":0,"direction":"flat"},"allVariants":{"normal":{"raw":{"current":1.34,"daily":{"changePct":0,"direction":"flat"},"weekly":{"changePct":0,"direction":"flat"},"monthly":{"changePct":0,"direction":"flat"}},"psa10":{"current":21,"daily":{"changePct":0,"direction":"flat"},"weekly":{"changePct":3.383536836952859e-14,"direction":"flat"},"monthly":{"changePct":3.383536836952859e-14,"direction":"flat"}}},"reverseHolofoil":{"raw":{"current":5.98,"daily":{"changePct":0,"direction":"flat"},"weekly":{"changePct":2.970496386956941e-14,"direction":"flat"},"monthly":{"changePct":1.4852481934784704e-14,"direction":"flat"}}}}},"ex2-23":{"variant":"normal","grade":"raw","current":2.6,"daily":{"changePct":0,"direction":"flat"},"weekly":{"changePct":0.22026431718063655,"direction":"flat"},"monthly":{"changePct":0.4566210045662066,"direction":"flat"},"allVariants":{"normal":{"raw":{"current":2.6,"daily":{"changePct":0,"direction":"flat"},"weekly":{"changePct":0.22026431718063655,"direction":"flat"},"monthly":{"changePct":0.4566210045662066,"direction":"flat"}},"psa10":{"current":124.47,"daily":{"changePct":0,"direction":"flat"},"weekly":{"changePct":0,"direction":"flat"},"monthly":{"changePct":1.1417092243273082e-14,"direction":"flat"}}},"reverseHolofoil":{"raw":{"current":18.73,"daily":{"changePct":0,"direction":"flat"},"weekly":{"changePct":1.8968038861721847e-14,"direction":"flat"},"monthly":{"changePct":1.8968038861721847e-14,"direction":"flat"}},"psa10":{"current":200.46,"daily":{"changePct":0,"direction":"flat"},"weekly":{"changePct":-2.835648950454355e-14,"direction":"flat"},"monthly":{"changePct":1.417824475227178e-14,"direction":"flat"}}}}},"ex2-24":{"variant":"normal","grade":"raw","current":29.33,"daily":{"changePct":1.7696044413601724,"direction":"up"},"weekly":{"changePct":1.5543136570031448,"direction":"up"},"monthly":{"changePct":4.0945331361943245,"direction":"up"},"allVariants":{"normal":{"raw":{"current":29.33,"daily":{"changePct":1.7696044413601724,"direction":"up"},"weekly":{"changePct":1.5543136570031448,"direction":"up"},"monthly":{"changePct":4.0945331361943245,"direction":"up"}},"psa10":{"current":490.63,"daily":{"changePct":0,"direction":"flat"},"weekly":{"changePct":45.04523147874419,"direction":"up"},"monthly":{"changePct":86.19716684088009,"direction":"up"}}},"reverseHolofoil":{"raw":{"current":80.38,"daily":{"changePct":0,"direction":"flat"},"weekly":{"changePct":0,"direction":"flat"},"monthly":{"changePct":-1.7679590339888034e-14,"direction":"flat"}},"psa10":{"current":3029.12,"daily":{"changePct":0,"direction":"flat"},"weekly":{"changePct":0,"direction":"flat"},"monthly":{"changePct":0,"direction":"flat"}}}}},"ex2-25":{"variant":"normal","grade":"raw","current":14.09,"daily":{"changePct":0.9312320916905372,"direction":"flat"},"weekly":{"changePct":0.4656160458452686,"direction":"flat"},"monthly":{"changePct":1.4811811736310294,"direction":"up"},"allVariants":{"normal":{"raw":{"current":14.09,"daily":{"changePct":0.9312320916905372,"direction":"flat"},"weekly":{"changePct":0.4656160458452686,"direction":"flat"},"monthly":{"changePct":1.4811811736310294,"direction":"up"}},"psa10":{"current":239.68,"daily":{"changePct":1.185818984913385e-14,"direction":"flat"},"weekly":{"changePct":-2.3126906863544328,"direction":"down"},"monthly":{"changePct":3.2295334172489163,"direction":"up"}}},"reverseHolofoil":{"raw":{"current":60,"daily":{"changePct":0,"direction":"flat"},"weekly":{"changePct":0,"direction":"flat"},"monthly":{"changePct":0,"direction":"flat"}},"psa10":{"current":61.41,"daily":{"changePct":0,"direction":"flat"},"weekly":{"changePct":-28.620294571841328,"direction":"down"},"monthly":{"changePct":-29.453178400546825,"direction":"down"}}}}},"ex2-26":{"variant":"normal","grade":"raw","current":1.28,"daily":{"changePct":0,"direction":"flat"},"weekly":{"changePct":0,"direction":"flat"},"monthly":{"changePct":0,"direction":"flat"},"allVariants":{"normal":{"raw":{"current":1.28,"daily":{"changePct":0,"direction":"flat"},"weekly":{"changePct":0,"direction":"flat"},"monthly":{"changePct":0,"direction":"flat"}},"psa10":{"current":69.97,"daily":{"changePct":0,"direction":"flat"},"weekly":{"changePct":2.0309925275406613e-14,"direction":"flat"},"monthly":{"changePct":2.030992527540661e-14,"direction":"flat"}}},"reverseHolofoil":{"raw":{"current":4.87,"daily":{"changePct":0,"direction":"flat"},"weekly":{"changePct":-1.8237749891173e-14,"direction":"flat"},"monthly":{"changePct":0.2995693690320184,"direction":"flat"}},"psa10":{"current":199.83,"daily":{"changePct":0,"direction":"flat"},"weekly":{"changePct":0,"direction":"flat"},"monthly":{"changePct":-1.422294421778712e-14,"direction":"flat"}}},"curranHill":{"raw":{"current":2.52,"daily":{"changePct":0,"direction":"flat"},"weekly":{"changePct":-1.76225876924628e-14,"direction":"flat"},"monthly":{"changePct":0,"direction":"flat"}}},"reedWeichler":{"raw":{"current":3.32,"daily":{"changePct":0,"direction":"flat"},"weekly":{"changePct":0,"direction":"flat"},"monthly":{"changePct":-4.397905759162306,"direction":"down"}}}}},"ex2-27":{"variant":"normal","grade":"raw","current":1.22,"daily":{"changePct":0,"direction":"flat"},"weekly":{"changePct":2.5210084033613276,"direction":"up"},"monthly":{"changePct":4.969436268960829,"direction":"up"},"allVariants":{"normal":{"raw":{"current":1.22,"daily":{"changePct":0,"direction":"flat"},"weekly":{"changePct":2.5210084033613276,"direction":"up"},"monthly":{"changePct":4.969436268960829,"direction":"up"}}},"reverseHolofoil":{"raw":{"current":6.86,"daily":{"changePct":0,"direction":"flat"},"weekly":{"changePct":4.074555700043348,"direction":"up"},"monthly":{"changePct":6.220900420469682,"direction":"up"}},"psa10":{"current":148.24,"daily":{"changePct":0,"direction":"flat"},"weekly":{"changePct":-50.25360269231138,"direction":"down"},"monthly":{"changePct":-27.770820369555537,"direction":"down"}}}}},"ex2-28":{"variant":"normal","grade":"raw","current":1.77,"daily":{"changePct":0,"direction":"flat"},"weekly":{"changePct":1.2544892933617589e-14,"direction":"flat"},"monthly":{"changePct":-0.6632653061224688,"direction":"flat"},"allVariants":{"normal":{"raw":{"current":1.77,"daily":{"changePct":0,"direction":"flat"},"weekly":{"changePct":1.2544892933617589e-14,"direction":"flat"},"monthly":{"changePct":-0.6632653061224688,"direction":"flat"}}},"reverseHolofoil":{"raw":{"current":6.47,"daily":{"changePct":0,"direction":"flat"},"weekly":{"changePct":2.745528345286323e-14,"direction":"flat"},"monthly":{"changePct":3.399680371930832,"direction":"up"}},"psa10":{"current":13,"daily":{"changePct":0,"direction":"flat"},"weekly":{"changePct":0,"direction":"flat"},"monthly":{"changePct":null,"direction":"flat"}}}}},"ex2-29":{"variant":"normal","grade":"raw","current":2.13,"daily":{"changePct":0,"direction":"flat"},"weekly":{"changePct":1.3596193065941489,"direction":"up"},"monthly":{"changePct":4.153640017865116,"direction":"up"},"allVariants":{"normal":{"raw":{"current":2.13,"daily":{"changePct":0,"direction":"flat"},"weekly":{"changePct":1.3596193065941489,"direction":"up"},"monthly":{"changePct":4.153640017865116,"direction":"up"}}},"reverseHolofoil":{"raw":{"current":13.19,"daily":{"changePct":0,"direction":"flat"},"weekly":{"changePct":0,"direction":"flat"},"monthly":{"changePct":1.3467451398030711e-14,"direction":"flat"}},"psa10":{"current":84.93,"daily":{"changePct":0,"direction":"flat"},"weekly":{"changePct":0,"direction":"flat"},"monthly":{"changePct":null,"direction":"flat"}}}}},"ex2-3":{"variant":"holofoil","grade":"raw","current":8.44,"daily":{"changePct":0,"direction":"flat"},"weekly":{"changePct":-4.70967741935483,"direction":"down"},"monthly":{"changePct":-4.894246011910723,"direction":"down"},"allVariants":{"holofoil":{"raw":{"current":8.44,"daily":{"changePct":0,"direction":"flat"},"weekly":{"changePct":-4.70967741935483,"direction":"down"},"monthly":{"changePct":-4.894246011910723,"direction":"down"}},"psa10":{"current":543.52,"daily":{"changePct":0,"direction":"flat"},"weekly":{"changePct":0,"direction":"flat"},"monthly":{"changePct":-2.0916771732708276e-14,"direction":"flat"}}},"reverseHolofoil":{"raw":{"current":8.37,"daily":{"changePct":0,"direction":"flat"},"weekly":{"changePct":0,"direction":"flat"},"monthly":{"changePct":2.470784641068463,"direction":"up"}},"psa10":{"current":196,"daily":{"changePct":0,"direction":"flat"},"weekly":{"changePct":0,"direction":"flat"},"monthly":{"changePct":0,"direction":"flat"}}}}},"ex2-30":{"variant":"normal","grade":"raw","current":1.56,"daily":{"changePct":0,"direction":"flat"},"weekly":{"changePct":0.3676470588235052,"direction":"flat"},"monthly":{"changePct":0.46082949308754145,"direction":"flat"},"allVariants":{"normal":{"raw":{"current":1.56,"daily":{"changePct":0,"direction":"flat"},"weekly":{"changePct":0.3676470588235052,"direction":"flat"},"monthly":{"changePct":0.46082949308754145,"direction":"flat"}}},"reverseHolofoil":{"raw":{"current":9.8,"daily":{"changePct":0,"direction":"flat"},"weekly":{"changePct":-1.8126090197961736e-14,"direction":"flat"},"monthly":{"changePct":-3.625218039592347e-14,"direction":"flat"}},"psa10":{"current":350,"daily":{"changePct":-1.6240976817373718e-14,"direction":"flat"},"weekly":{"changePct":1.624097681737372e-14,"direction":"flat"},"monthly":{"changePct":3.248195363474744e-14,"direction":"flat"}}}}},"ex2-31":{"variant":"normal","grade":"raw","current":6.6,"daily":{"changePct":-1.3452914798206257,"direction":"down"},"weekly":{"changePct":-0.8842957596420051,"direction":"flat"},"monthly":{"changePct":-0.6702464652708121,"direction":"flat"},"allVariants":{"normal":{"raw":{"current":6.6,"daily":{"changePct":-1.3452914798206257,"direction":"down"},"weekly":{"changePct":-0.8842957596420051,"direction":"flat"},"monthly":{"changePct":-0.6702464652708121,"direction":"flat"}}},"reverseHolofoil":{"raw":{"current":34.31,"daily":{"changePct":0,"direction":"flat"},"weekly":{"changePct":0,"direction":"flat"},"monthly":{"changePct":-2.0709493901489364e-14,"direction":"flat"}},"psa10":{"current":250,"daily":{"changePct":0,"direction":"flat"},"weekly":{"changePct":0,"direction":"flat"},"monthly":{"changePct":0,"direction":"flat"}}}}},"ex2-32":{"variant":"normal","grade":"raw","current":1.46,"daily":{"changePct":0,"direction":"flat"},"weekly":{"changePct":0.3929273084479419,"direction":"flat"},"monthly":{"changePct":-0.07125044531527716,"direction":"flat"},"allVariants":{"normal":{"raw":{"current":1.46,"daily":{"changePct":0,"direction":"flat"},"weekly":{"changePct":0.3929273084479419,"direction":"flat"},"monthly":{"changePct":-0.07125044531527716,"direction":"flat"}}},"reverseHolofoil":{"raw":{"current":5.22,"daily":{"changePct":0,"direction":"flat"},"weekly":{"changePct":1.7014912254791673e-14,"direction":"flat"},"monthly":{"changePct":3.402982450958335e-14,"direction":"flat"}},"psa10":{"current":1195,"daily":{"changePct":0,"direction":"flat"},"weekly":{"changePct":3.8054171622298264e-14,"direction":"flat"},"monthly":{"changePct":3.8054171622298264e-14,"direction":"flat"}}}}},"ex2-33":{"variant":"normal","grade":"raw","current":1.76,"daily":{"changePct":1.1494252873563229,"direction":"up"},"weekly":{"changePct":2.7684563758389267,"direction":"up"},"monthly":{"changePct":2.380952380952383,"direction":"up"},"allVariants":{"normal":{"raw":{"current":1.76,"daily":{"changePct":1.1494252873563229,"direction":"up"},"weekly":{"changePct":2.7684563758389267,"direction":"up"},"monthly":{"changePct":2.380952380952383,"direction":"up"}},"psa10":{"current":25.12,"daily":{"changePct":0,"direction":"flat"},"weekly":{"changePct":0,"direction":"flat"},"monthly":{"changePct":0,"direction":"flat"}}},"reverseHolofoil":{"raw":{"current":8.63,"daily":{"changePct":0,"direction":"flat"},"weekly":{"changePct":2.058350914716397e-14,"direction":"flat"},"monthly":{"changePct":8.503829009029594,"direction":"up"}}}}},"ex2-34":{"variant":"normal","grade":"raw","current":1.7,"daily":{"changePct":0,"direction":"flat"},"weekly":{"changePct":0.5917159763313483,"direction":"flat"},"monthly":{"changePct":0.3309729064039143,"direction":"flat"},"allVariants":{"normal":{"raw":{"current":1.7,"daily":{"changePct":0,"direction":"flat"},"weekly":{"changePct":0.5917159763313483,"direction":"flat"},"monthly":{"changePct":0.3309729064039143,"direction":"flat"}}},"reverseHolofoil":{"raw":{"current":5.47,"daily":{"changePct":0,"direction":"flat"},"weekly":{"changePct":0,"direction":"flat"},"monthly":{"changePct":-3.2474530884830894e-14,"direction":"flat"}},"psa10":{"current":69.9,"daily":{"changePct":0,"direction":"flat"},"weekly":{"changePct":0,"direction":"flat"},"monthly":{"changePct":null,"direction":"flat"}}}}},"ex2-35":{"variant":"normal","grade":"raw","current":1.95,"daily":{"changePct":1.0362694300518145,"direction":"up"},"weekly":{"changePct":0.4437869822485492,"direction":"flat"},"monthly":{"changePct":1.8755561640084775,"direction":"up"},"allVariants":{"normal":{"raw":{"current":1.95,"daily":{"changePct":1.0362694300518145,"direction":"up"},"weekly":{"changePct":0.4437869822485492,"direction":"flat"},"monthly":{"changePct":1.8755561640084775,"direction":"up"}},"psa10":{"current":599.99,"daily":{"changePct":0,"direction":"flat"},"weekly":{"changePct":0,"direction":"flat"},"monthly":{"changePct":-3.7896244177941634e-14,"direction":"flat"}}},"reverseHolofoil":{"raw":{"current":15.27,"daily":{"changePct":0,"direction":"flat"},"weekly":{"changePct":1.1632985195810417e-14,"direction":"flat"},"monthly":{"changePct":3.4552845528454905,"direction":"up"}},"psa10":{"current":347.5,"daily":{"changePct":0,"direction":"flat"},"weekly":{"changePct":0,"direction":"flat"},"monthly":{"changePct":0,"direction":"flat"}}}}},"ex2-36":{"variant":"normal","grade":"raw","current":2.41,"daily":{"changePct":0,"direction":"flat"},"weekly":{"changePct":0.4166666666666763,"direction":"flat"},"monthly":{"changePct":0.23294869711253802,"direction":"flat"},"allVariants":{"normal":{"raw":{"current":2.41,"daily":{"changePct":0,"direction":"flat"},"weekly":{"changePct":0.4166666666666763,"direction":"flat"},"monthly":{"changePct":0.23294869711253802,"direction":"flat"}}},"reverseHolofoil":{"raw":{"current":9.22,"daily":{"changePct":0,"direction":"flat"},"weekly":{"changePct":-1.926634316052332e-14,"direction":"flat"},"monthly":{"changePct":-1.926634316052332e-14,"direction":"flat"}},"psa10":{"current":40.01,"daily":{"changePct":0,"direction":"flat"},"weekly":{"changePct":0,"direction":"flat"},"monthly":{"changePct":null,"direction":"flat"}}}}},"ex2-37":{"variant":"normal","grade":"raw","current":2.08,"daily":{"changePct":0.9708737864077678,"direction":"flat"},"weekly":{"changePct":-0.20661157024792032,"direction":"flat"},"monthly":{"changePct":2.4568606068381613,"direction":"up"},"allVariants":{"normal":{"raw":{"current":2.08,"daily":{"changePct":0.9708737864077678,"direction":"flat"},"weekly":{"changePct":-0.20661157024792032,"direction":"flat"},"monthly":{"changePct":2.4568606068381613,"direction":"up"}}},"reverseHolofoil":{"raw":{"current":9.54,"daily":{"changePct":8.532423208191126,"direction":"up"},"weekly":{"changePct":4.266211604095563,"direction":"up"},"monthly":{"changePct":2.362275314895334,"direction":"up"}},"psa10":{"current":30.88,"daily":{"changePct":0,"direction":"flat"},"weekly":{"changePct":0,"direction":"flat"},"monthly":{"changePct":null,"direction":"flat"}}}}},"ex2-38":{"variant":"normal","grade":"raw","current":2.25,"daily":{"changePct":0,"direction":"flat"},"weekly":{"changePct":1.0262989095574009,"direction":"up"},"monthly":{"changePct":3.0799475753604204,"direction":"up"},"allVariants":{"normal":{"raw":{"current":2.25,"daily":{"changePct":0,"direction":"flat"},"weekly":{"changePct":1.0262989095574009,"direction":"up"},"monthly":{"changePct":3.0799475753604204,"direction":"up"}},"psa10":{"current":116.69,"daily":{"changePct":1.2178296953639563e-14,"direction":"flat"},"weekly":{"changePct":1.2178296953639563e-14,"direction":"flat"},"monthly":{"changePct":0,"direction":"flat"}}},"reverseHolofoil":{"raw":{"current":5,"daily":{"changePct":0,"direction":"flat"},"weekly":{"changePct":0,"direction":"flat"},"monthly":{"changePct":0,"direction":"flat"}},"psa10":{"current":168,"daily":{"changePct":0,"direction":"flat"},"weekly":{"changePct":3.383536836952859e-14,"direction":"flat"},"monthly":{"changePct":3.383536836952859e-14,"direction":"flat"}}}}},"ex2-39":{"variant":"normal","grade":"raw","current":3.06,"daily":{"changePct":0,"direction":"flat"},"weekly":{"changePct":0.327868852459024,"direction":"flat"},"monthly":{"changePct":1.0575641631916084,"direction":"up"},"allVariants":{"normal":{"raw":{"current":3.06,"daily":{"changePct":0,"direction":"flat"},"weekly":{"changePct":0.327868852459024,"direction":"flat"},"monthly":{"changePct":1.0575641631916084,"direction":"up"}},"psa10":{"current":75,"daily":{"changePct":0,"direction":"flat"},"weekly":{"changePct":-1.8947806286936e-14,"direction":"flat"},"monthly":{"changePct":-1.8947806286936e-14,"direction":"flat"}}},"reverseHolofoil":{"raw":{"current":12,"daily":{"changePct":0,"direction":"flat"},"weekly":{"changePct":0,"direction":"flat"},"monthly":{"changePct":23.36448598130842,"direction":"up"}}}}},"ex2-4":{"variant":"holofoil","grade":"raw","current":24.62,"daily":{"changePct":0,"direction":"flat"},"weekly":{"changePct":0,"direction":"flat"},"monthly":{"changePct":0.25543256950357146,"direction":"flat"},"allVariants":{"holofoil":{"raw":{"current":24.62,"daily":{"changePct":0,"direction":"flat"},"weekly":{"changePct":0,"direction":"flat"},"monthly":{"changePct":0.25543256950357146,"direction":"flat"}},"psa10":{"current":1139.82,"daily":{"changePct":0,"direction":"flat"},"weekly":{"changePct":45.73120948607938,"direction":"up"},"monthly":{"changePct":234.44516225680192,"direction":"up"}}},"reverseHolofoil":{"raw":{"current":22.99,"daily":{"changePct":1.5453300038279695e-14,"direction":"flat"},"weekly":{"changePct":6.597337219315065,"direction":"up"},"monthly":{"changePct":8.675958188153327,"direction":"up"}},"psa10":{"current":103,"daily":{"changePct":0,"direction":"flat"},"weekly":{"changePct":-1.3796946325438837e-14,"direction":"flat"},"monthly":{"changePct":-1.3796946325438837e-14,"direction":"flat"}}}}},"ex2-40":{"variant":"normal","grade":"raw","current":4.94,"daily":{"changePct":0,"direction":"flat"},"weekly":{"changePct":1.7979320236844644e-14,"direction":"flat"},"monthly":{"changePct":1.7979320236844644e-14,"direction":"flat"},"allVariants":{"normal":{"raw":{"current":4.94,"daily":{"changePct":0,"direction":"flat"},"weekly":{"changePct":1.7979320236844644e-14,"direction":"flat"},"monthly":{"changePct":1.7979320236844644e-14,"direction":"flat"}}},"reverseHolofoil":{"raw":{"current":15.64,"daily":{"changePct":0,"direction":"flat"},"weekly":{"changePct":-1.1357780303070654e-14,"direction":"flat"},"monthly":{"changePct":8.927440800303895,"direction":"up"}},"psa10":{"current":466,"daily":{"changePct":1.2198158553821464e-14,"direction":"flat"},"weekly":{"changePct":1.2198158553821464e-14,"direction":"flat"},"monthly":{"changePct":0,"direction":"flat"}}}}},"ex2-41":{"variant":"normal","grade":"raw","current":2.62,"daily":{"changePct":0.7692307692307698,"direction":"flat"},"weekly":{"changePct":5.363321799307983,"direction":"up"},"monthly":{"changePct":5.712126120289368,"direction":"up"},"allVariants":{"normal":{"raw":{"current":2.62,"daily":{"changePct":0.7692307692307698,"direction":"flat"},"weekly":{"changePct":5.363321799307983,"direction":"up"},"monthly":{"changePct":5.712126120289368,"direction":"up"}},"psa10":{"current":89.97,"daily":{"changePct":0,"direction":"flat"},"weekly":{"changePct":0,"direction":"flat"},"monthly":{"changePct":1.5795103606982332e-14,"direction":"flat"}}},"reverseHolofoil":{"raw":{"current":10,"daily":{"changePct":0,"direction":"flat"},"weekly":{"changePct":0,"direction":"flat"},"monthly":{"changePct":0,"direction":"flat"}}}}},"ex2-42":{"variant":"normal","grade":"raw","current":1.09,"daily":{"changePct":0,"direction":"flat"},"weekly":{"changePct":0,"direction":"flat"},"monthly":{"changePct":-0.08333333333333895,"direction":"flat"},"allVariants":{"normal":{"raw":{"current":1.09,"daily":{"changePct":0,"direction":"flat"},"weekly":{"changePct":0,"direction":"flat"},"monthly":{"changePct":-0.08333333333333895,"direction":"flat"}}},"reverseHolofoil":{"raw":{"current":5.99,"daily":{"changePct":0,"direction":"flat"},"weekly":{"changePct":0,"direction":"flat"},"monthly":{"changePct":-1.4827686472456175e-14,"direction":"flat"}},"psa10":{"current":511.01,"daily":{"changePct":0,"direction":"flat"},"weekly":{"changePct":2.2247478077066216e-14,"direction":"flat"},"monthly":{"changePct":2.224747807706621e-14,"direction":"flat"}}}}},"ex2-43":{"variant":"normal","grade":"raw","current":2.19,"daily":{"changePct":0,"direction":"flat"},"weekly":{"changePct":2.027804611187501e-14,"direction":"flat"},"monthly":{"changePct":2.027804611187501e-14,"direction":"flat"},"allVariants":{"normal":{"raw":{"current":2.19,"daily":{"changePct":0,"direction":"flat"},"weekly":{"changePct":2.027804611187501e-14,"direction":"flat"},"monthly":{"changePct":2.027804611187501e-14,"direction":"flat"}}},"reverseHolofoil":{"raw":{"current":3.79,"daily":{"changePct":0,"direction":"flat"},"weekly":{"changePct":-1.1717393399737797e-14,"direction":"flat"},"monthly":{"changePct":-10.517278385919733,"direction":"down"}},"psa10":{"current":39,"daily":{"changePct":0,"direction":"flat"},"weekly":{"changePct":0,"direction":"flat"},"monthly":{"changePct":null,"direction":"flat"}}}}},"ex2-44":{"variant":"normal","grade":"raw","current":2.19,"daily":{"changePct":0,"direction":"flat"},"weekly":{"changePct":-0.9049773755656116,"direction":"flat"},"monthly":{"changePct":-2.970922882427309,"direction":"down"},"allVariants":{"normal":{"raw":{"current":2.19,"daily":{"changePct":0,"direction":"flat"},"weekly":{"changePct":-0.9049773755656116,"direction":"flat"},"monthly":{"changePct":-2.970922882427309,"direction":"down"}}},"reverseHolofoil":{"raw":{"current":4.64,"daily":{"changePct":0,"direction":"flat"},"weekly":{"changePct":1.9141776286640637e-14,"direction":"flat"},"monthly":{"changePct":3.8283552573281275e-14,"direction":"flat"}},"psa10":{"current":379,"daily":{"changePct":1.4998263551664387e-14,"direction":"flat"},"weekly":{"changePct":1.4998263551664387e-14,"direction":"flat"},"monthly":{"changePct":-2.999652710332876e-14,"direction":"flat"}}}}},"ex2-45":{"variant":"normal","grade":"raw","current":2.36,"daily":{"changePct":0,"direction":"flat"},"weekly":{"changePct":0.9779951100244426,"direction":"flat"},"monthly":{"changePct":1.0291978968564894,"direction":"up"},"allVariants":{"normal":{"raw":{"current":2.36,"daily":{"changePct":0,"direction":"flat"},"weekly":{"changePct":0.9779951100244426,"direction":"flat"},"monthly":{"changePct":1.0291978968564894,"direction":"up"}}},"reverseHolofoil":{"raw":{"current":20.12,"daily":{"changePct":0,"direction":"flat"},"weekly":{"changePct":0.6503251625813035,"direction":"flat"},"monthly":{"changePct":0.18580718930895912,"direction":"flat"}},"psa10":{"current":720,"daily":{"changePct":860,"direction":"up"},"weekly":{"changePct":430,"direction":"up"},"monthly":{"changePct":null,"direction":"flat"}}},"michaelGonzalez":{"raw":{"current":7.68,"daily":{"changePct":0,"direction":"flat"},"weekly":{"changePct":1.587301587301589,"direction":"up"},"monthly":{"changePct":8.80372863801138,"direction":"up"}}}}},"ex2-46":{"variant":"normal","grade":"raw","current":2.52,"daily":{"changePct":0,"direction":"flat"},"weekly":{"changePct":-0.3389830508474354,"direction":"flat"},"monthly":{"changePct":0.26779276959522896,"direction":"flat"},"allVariants":{"normal":{"raw":{"current":2.52,"daily":{"changePct":0,"direction":"flat"},"weekly":{"changePct":-0.3389830508474354,"direction":"flat"},"monthly":{"changePct":0.26779276959522896,"direction":"flat"}}},"reverseHolofoil":{"raw":{"current":6.82,"daily":{"changePct":1.3023143983872805e-14,"direction":"flat"},"weekly":{"changePct":-1.3023143983872802e-14,"direction":"flat"},"monthly":{"changePct":4.3393602225312735,"direction":"up"}},"psa10":{"current":87.5,"daily":{"changePct":-1.6240976817373718e-14,"direction":"flat"},"weekly":{"changePct":-1.6240976817373718e-14,"direction":"flat"},"monthly":{"changePct":null,"direction":"flat"}}}}},"ex2-47":{"variant":"normal","grade":"raw","current":1.46,"daily":{"changePct":0,"direction":"flat"},"weekly":{"changePct":-0.19531249999998718,"direction":"flat"},"monthly":{"changePct":-0.9253547193090856,"direction":"flat"},"allVariants":{"normal":{"raw":{"current":1.46,"daily":{"changePct":0,"direction":"flat"},"weekly":{"changePct":-0.19531249999998718,"direction":"flat"},"monthly":{"changePct":-0.9253547193090856,"direction":"flat"}}},"reverseHolofoil":{"raw":{"current":9.9,"daily":{"changePct":0,"direction":"flat"},"weekly":{"changePct":24.505928853754924,"direction":"up"},"monthly":{"changePct":38.99045461899368,"direction":"up"}},"psa10":{"current":75,"daily":{"changePct":0,"direction":"flat"},"weekly":{"changePct":0,"direction":"flat"},"monthly":{"changePct":null,"direction":"flat"}}}}},"ex2-48":{"variant":"normal","grade":"raw","current":0.66,"daily":{"changePct":0,"direction":"flat"},"weekly":{"changePct":3.3643121958338087e-14,"direction":"flat"},"monthly":{"changePct":1.2552301255230294,"direction":"up"},"allVariants":{"normal":{"raw":{"current":0.66,"daily":{"changePct":0,"direction":"flat"},"weekly":{"changePct":3.3643121958338087e-14,"direction":"flat"},"monthly":{"changePct":1.2552301255230294,"direction":"up"}}},"reverseHolofoil":{"raw":{"current":2.77,"daily":{"changePct":0,"direction":"flat"},"weekly":{"changePct":-1.6032101438630417e-14,"direction":"flat"},"monthly":{"changePct":-1.6032101438630417e-14,"direction":"flat"}},"psa10":{"current":152.48,"daily":{"changePct":0,"direction":"flat"},"weekly":{"changePct":0.005621662138087072,"direction":"flat"},"monthly":{"changePct":0.01124416708832336,"direction":"flat"}}}}},"ex2-49":{"variant":"normal","grade":"raw","current":2.13,"daily":{"changePct":0,"direction":"flat"},"weekly":{"changePct":-2.0849258678406692e-14,"direction":"flat"},"monthly":{"changePct":0.04269854824934155,"direction":"flat"},"allVariants":{"normal":{"raw":{"current":2.13,"daily":{"changePct":0,"direction":"flat"},"weekly":{"changePct":-2.0849258678406692e-14,"direction":"flat"},"monthly":{"changePct":0.04269854824934155,"direction":"flat"}}},"reverseHolofoil":{"raw":{"current":6.13,"daily":{"changePct":0,"direction":"flat"},"weekly":{"changePct":0,"direction":"flat"},"monthly":{"changePct":1.448904436704935e-14,"direction":"flat"}},"psa10":{"current":12,"daily":{"changePct":0,"direction":"flat"},"weekly":{"changePct":0,"direction":"flat"},"monthly":{"changePct":null,"direction":"flat"}}}}},"ex2-5":{"variant":"holofoil","grade":"raw","current":74.92,"daily":{"changePct":0,"direction":"flat"},"weekly":{"changePct":1.8968038861721847e-14,"direction":"flat"},"monthly":{"changePct":1.8968038861721847e-14,"direction":"flat"},"allVariants":{"holofoil":{"raw":{"current":74.92,"daily":{"changePct":0,"direction":"flat"},"weekly":{"changePct":1.8968038861721847e-14,"direction":"flat"},"monthly":{"changePct":1.8968038861721847e-14,"direction":"flat"}},"psa10":{"current":2728.14,"daily":{"changePct":0,"direction":"flat"},"weekly":{"changePct":-2.3646322066679506,"direction":"down"},"monthly":{"changePct":-6.2894975299630715,"direction":"down"}}},"reverseHolofoil":{"raw":{"current":54.99,"daily":{"changePct":0,"direction":"flat"},"weekly":{"changePct":-0.27720207253887486,"direction":"flat"},"monthly":{"changePct":-1.7381698858006327,"direction":"down"}},"psa10":{"current":2990.6,"daily":{"changePct":0,"direction":"flat"},"weekly":{"changePct":99.47059899684416,"direction":"up"},"monthly":{"changePct":489.577510233024,"direction":"up"}}}}},"ex2-50":{"variant":"normal","grade":"raw","current":1.23,"daily":{"changePct":6.034482758620696,"direction":"up"},"weekly":{"changePct":3.0172413793103576,"direction":"up"},"monthly":{"changePct":1.4984227129337784,"direction":"up"},"allVariants":{"normal":{"raw":{"current":1.23,"daily":{"changePct":6.034482758620696,"direction":"up"},"weekly":{"changePct":3.0172413793103576,"direction":"up"},"monthly":{"changePct":1.4984227129337784,"direction":"up"}},"psa10":{"current":79,"daily":{"changePct":0,"direction":"flat"},"weekly":{"changePct":0,"direction":"flat"},"monthly":{"changePct":-1.7988423690129117e-14,"direction":"flat"}}},"reverseHolofoil":{"raw":{"current":6.63,"daily":{"changePct":0,"direction":"flat"},"weekly":{"changePct":2.6792712509807708e-14,"direction":"flat"},"monthly":{"changePct":0,"direction":"flat"}}}}},"ex2-51":{"variant":"normal","grade":"raw","current":3,"daily":{"changePct":0,"direction":"flat"},"weekly":{"changePct":0,"direction":"flat"},"monthly":{"changePct":0.12135922330096423,"direction":"flat"},"allVariants":{"normal":{"raw":{"current":3,"daily":{"changePct":0,"direction":"flat"},"weekly":{"changePct":0,"direction":"flat"},"monthly":{"changePct":0.12135922330096423,"direction":"flat"}},"psa10":{"current":137.54,"daily":{"changePct":0,"direction":"flat"},"weekly":{"changePct":2.0664322691874375e-14,"direction":"flat"},"monthly":{"changePct":0,"direction":"flat"}}},"reverseHolofoil":{"raw":{"current":26.35,"daily":{"changePct":-1.3482784359774193e-14,"direction":"flat"},"weekly":{"changePct":-2.6965568719548384e-14,"direction":"flat"},"monthly":{"changePct":-2.6965568719548384e-14,"direction":"flat"}},"psa10":{"current":782,"daily":{"changePct":0,"direction":"flat"},"weekly":{"changePct":0,"direction":"flat"},"monthly":{"changePct":1.453795878793044e-14,"direction":"flat"}}},"nonEreader":{"raw":{"current":5.2,"daily":{"changePct":0,"direction":"flat"},"weekly":{"changePct":1.708035422500241e-14,"direction":"flat"},"monthly":{"changePct":0,"direction":"flat"}}}}},"ex2-52":{"variant":"normal","grade":"raw","current":0.95,"daily":{"changePct":0,"direction":"flat"},"weekly":{"changePct":-0.1501501501501403,"direction":"flat"},"monthly":{"changePct":-0.6653992395437016,"direction":"flat"},"allVariants":{"normal":{"raw":{"current":0.95,"daily":{"changePct":0,"direction":"flat"},"weekly":{"changePct":-0.1501501501501403,"direction":"flat"},"monthly":{"changePct":-0.6653992395437016,"direction":"flat"}},"psa10":{"current":55,"daily":{"changePct":0,"direction":"flat"},"weekly":{"changePct":0,"direction":"flat"},"monthly":{"changePct":null,"direction":"flat"}}},"reverseHolofoil":{"raw":{"current":4.3,"daily":{"changePct":0,"direction":"flat"},"weekly":{"changePct":0,"direction":"flat"},"monthly":{"changePct":0,"direction":"flat"}}}}},"ex2-53":{"variant":"normal","grade":"raw","current":1.48,"daily":{"changePct":0,"direction":"flat"},"weekly":{"changePct":1.5003013846285902e-14,"direction":"flat"},"monthly":{"changePct":-1.8685955394815945,"direction":"down"},"allVariants":{"normal":{"raw":{"current":1.48,"daily":{"changePct":0,"direction":"flat"},"weekly":{"changePct":1.5003013846285902e-14,"direction":"flat"},"monthly":{"changePct":-1.8685955394815945,"direction":"down"}}},"reverseHolofoil":{"raw":{"current":12.99,"daily":{"changePct":0,"direction":"flat"},"weekly":{"changePct":0,"direction":"flat"},"monthly":{"changePct":11.772528160200226,"direction":"up"}},"psa10":{"current":200,"daily":{"changePct":0,"direction":"flat"},"weekly":{"changePct":0,"direction":"flat"},"monthly":{"changePct":0,"direction":"flat"}}}}},"ex2-54":{"variant":"normal","grade":"raw","current":4.53,"daily":{"changePct":0.22123893805311232,"direction":"flat"},"weekly":{"changePct":1.2951710905021283,"direction":"up"},"monthly":{"changePct":5.66617951528437,"direction":"up"},"allVariants":{"normal":{"raw":{"current":4.53,"daily":{"changePct":0.22123893805311232,"direction":"flat"},"weekly":{"changePct":1.2951710905021283,"direction":"up"},"monthly":{"changePct":5.66617951528437,"direction":"up"}},"psa10":{"current":55,"daily":{"changePct":0,"direction":"flat"},"weekly":{"changePct":0,"direction":"flat"},"monthly":{"changePct":-2.5837917664003636e-14,"direction":"flat"}}},"reverseHolofoil":{"raw":{"current":5.54,"daily":{"changePct":0,"direction":"flat"},"weekly":{"changePct":0.20671834625321633,"direction":"flat"},"monthly":{"changePct":0.7272727272727442,"direction":"flat"}}}}},"ex2-55":{"variant":"normal","grade":"raw","current":1.03,"daily":{"changePct":0,"direction":"flat"},"weekly":{"changePct":-0.4143646408839722,"direction":"flat"},"monthly":{"changePct":-0.8241758241758127,"direction":"flat"},"allVariants":{"normal":{"raw":{"current":1.03,"daily":{"changePct":0,"direction":"flat"},"weekly":{"changePct":-0.4143646408839722,"direction":"flat"},"monthly":{"changePct":-0.8241758241758127,"direction":"flat"}}},"reverseHolofoil":{"raw":{"current":8.44,"daily":{"changePct":0,"direction":"flat"},"weekly":{"changePct":10.100633619083114,"direction":"up"},"monthly":{"changePct":47.29493891797557,"direction":"up"}},"psa10":{"current":20.11,"daily":{"changePct":0,"direction":"flat"},"weekly":{"changePct":0,"direction":"flat"},"monthly":{"changePct":null,"direction":"flat"}}},"nonEreader":{"raw":{"current":1.03,"daily":{"changePct":0,"direction":"flat"},"weekly":{"changePct":2.155772863349819e-14,"direction":"flat"},"monthly":{"changePct":-9.577015163607328,"direction":"down"}}}}},"ex2-56":{"variant":"normal","grade":"raw","current":1.23,"daily":{"changePct":0,"direction":"flat"},"weekly":{"changePct":-1.3745704467353939,"direction":"down"},"monthly":{"changePct":-1.7006802721088197,"direction":"down"},"allVariants":{"normal":{"raw":{"current":1.23,"daily":{"changePct":0,"direction":"flat"},"weekly":{"changePct":-1.3745704467353939,"direction":"down"},"monthly":{"changePct":-1.7006802721088197,"direction":"down"}},"psa10":{"current":6.5,"daily":{"changePct":0,"direction":"flat"},"weekly":{"changePct":0,"direction":"flat"},"monthly":{"changePct":null,"direction":"flat"}}},"reverseHolofoil":{"raw":{"current":5.89,"daily":{"changePct":0,"direction":"flat"},"weekly":{"changePct":1.5079429876063252e-14,"direction":"flat"},"monthly":{"changePct":1.5079429876063252e-14,"direction":"flat"}},"psa10":{"current":12,"daily":{"changePct":0,"direction":"flat"},"weekly":{"changePct":0,"direction":"flat"},"monthly":{"changePct":null,"direction":"flat"}}}}},"ex2-57":{"variant":"normal","grade":"raw","current":0.62,"daily":{"changePct":0,"direction":"flat"},"weekly":{"changePct":-1.79068229778251e-14,"direction":"flat"},"monthly":{"changePct":-3.5813645955650197e-14,"direction":"flat"},"allVariants":{"normal":{"raw":{"current":0.62,"daily":{"changePct":0,"direction":"flat"},"weekly":{"changePct":-1.79068229778251e-14,"direction":"flat"},"monthly":{"changePct":-3.5813645955650197e-14,"direction":"flat"}},"psa10":{"current":55,"daily":{"changePct":0,"direction":"flat"},"weekly":{"changePct":0,"direction":"flat"},"monthly":{"changePct":-2.5837917664003636e-14,"direction":"flat"}}},"reverseHolofoil":{"raw":{"current":3.84,"daily":{"changePct":0,"direction":"flat"},"weekly":{"changePct":4.347826086956538,"direction":"up"},"monthly":{"changePct":5.617977528089866,"direction":"up"}},"psa10":{"current":375,"daily":{"changePct":0,"direction":"flat"},"weekly":{"changePct":0,"direction":"flat"},"monthly":{"changePct":0,"direction":"flat"}}}}},"ex2-58":{"variant":"normal","grade":"raw","current":0.94,"daily":{"changePct":0,"direction":"flat"},"weekly":{"changePct":-0.3030303030303184,"direction":"flat"},"monthly":{"changePct":-1.7110266159695928,"direction":"down"},"allVariants":{"normal":{"raw":{"current":0.94,"daily":{"changePct":0,"direction":"flat"},"weekly":{"changePct":-0.3030303030303184,"direction":"flat"},"monthly":{"changePct":-1.7110266159695928,"direction":"down"}},"psa10":{"current":16.25,"daily":{"changePct":0,"direction":"flat"},"weekly":{"changePct":0,"direction":"flat"},"monthly":{"changePct":null,"direction":"flat"}}},"reverseHolofoil":{"raw":{"current":5.4,"daily":{"changePct":0,"direction":"flat"},"weekly":{"changePct":1.6447748512965283e-14,"direction":"flat"},"monthly":{"changePct":1.9917582417582593,"direction":"up"}},"psa10":{"current":47.32,"daily":{"changePct":0,"direction":"flat"},"weekly":{"changePct":0,"direction":"flat"},"monthly":{"changePct":null,"direction":"flat"}}}}},"ex2-59":{"variant":"normal","grade":"raw","current":1.58,"daily":{"changePct":1.9354838709677438,"direction":"up"},"weekly":{"changePct":1.3413506012950953,"direction":"up"},"monthly":{"changePct":4.761904761904772,"direction":"up"},"allVariants":{"normal":{"raw":{"current":1.58,"daily":{"changePct":1.9354838709677438,"direction":"up"},"weekly":{"changePct":1.3413506012950953,"direction":"up"},"monthly":{"changePct":4.761904761904772,"direction":"up"}},"psa10":{"current":173.04,"daily":{"changePct":0,"direction":"flat"},"weekly":{"changePct":65.58398950131233,"direction":"up"},"monthly":{"changePct":157.5803778588001,"direction":"up"}}},"reverseHolofoil":{"raw":{"current":18.6,"daily":{"changePct":0,"direction":"flat"},"weekly":{"changePct":-0.15337423312881476,"direction":"flat"},"monthly":{"changePct":-0.1914975105323577,"direction":"flat"}},"psa10":{"current":149,"daily":{"changePct":0,"direction":"flat"},"weekly":{"changePct":0,"direction":"flat"},"monthly":{"changePct":-1.9074972772083224e-14,"direction":"flat"}}}}},"ex2-6":{"variant":"holofoil","grade":"raw","current":71.19,"daily":{"changePct":0,"direction":"flat"},"weekly":{"changePct":-1.996186924455963e-14,"direction":"flat"},"monthly":{"changePct":-1.996186924455963e-14,"direction":"flat"},"allVariants":{"holofoil":{"raw":{"current":71.19,"daily":{"changePct":0,"direction":"flat"},"weekly":{"changePct":-1.996186924455963e-14,"direction":"flat"},"monthly":{"changePct":-1.996186924455963e-14,"direction":"flat"}},"psa10":{"current":2275.64,"daily":{"changePct":0,"direction":"flat"},"weekly":{"changePct":41.58002421070782,"direction":"up"},"monthly":{"changePct":186.62501944733665,"direction":"up"}}},"reverseHolofoil":{"raw":{"current":104.5,"daily":{"changePct":1.359890403368613e-14,"direction":"flat"},"weekly":{"changePct":-1.3598904033686125e-14,"direction":"flat"},"monthly":{"changePct":1.3598904033686133e-14,"direction":"flat"}},"psa10":{"current":3280,"daily":{"changePct":0,"direction":"flat"},"weekly":{"changePct":90.77182825217774,"direction":"up"},"monthly":{"changePct":355.45354923851,"direction":"up"}}}}},"ex2-60":{"variant":"normal","grade":"raw","current":1.68,"daily":{"changePct":0.5988023952095813,"direction":"flat"},"weekly":{"changePct":0.3852739726027544,"direction":"flat"},"monthly":{"changePct":0.6333567909922502,"direction":"flat"},"allVariants":{"normal":{"raw":{"current":1.68,"daily":{"changePct":0.5988023952095813,"direction":"flat"},"weekly":{"changePct":0.3852739726027544,"direction":"flat"},"monthly":{"changePct":0.6333567909922502,"direction":"flat"}}},"reverseHolofoil":{"raw":{"current":4.81,"daily":{"changePct":8.823529411764698,"direction":"up"},"weekly":{"changePct":4.4117647058823595,"direction":"up"},"monthly":{"changePct":11.740483755917253,"direction":"up"}},"psa10":{"current":412,"daily":{"changePct":0,"direction":"flat"},"weekly":{"changePct":-1.3796946325438837e-14,"direction":"flat"},"monthly":{"changePct":-1.3796946325438837e-14,"direction":"flat"}}},"chrisFulop":{"raw":{"current":1.48,"daily":{"changePct":0,"direction":"flat"},"weekly":{"changePct":1.5003013846285902e-14,"direction":"flat"},"monthly":{"changePct":33.44262295081971,"direction":"up"}}},"kevinNguyen":{"raw":{"current":3.51,"daily":{"changePct":1.2652114240742528e-14,"direction":"flat"},"weekly":{"changePct":2.5304228481485058e-14,"direction":"flat"},"monthly":{"changePct":0,"direction":"flat"}}},"michaelGonzalez":{"raw":{"current":2.65,"daily":{"changePct":0,"direction":"flat"},"weekly":{"changePct":0,"direction":"flat"},"monthly":{"changePct":0,"direction":"flat"}}},"nonEreader":{"raw":{"current":3,"daily":{"changePct":0,"direction":"flat"},"weekly":{"changePct":0,"direction":"flat"},"monthly":{"changePct":0,"direction":"flat"}}},"reedWeichler":{"raw":{"current":2.87,"daily":{"changePct":0,"direction":"flat"},"weekly":{"changePct":0,"direction":"flat"},"monthly":{"changePct":5.338672005338707,"direction":"up"}}},"takashiYoneda":{"raw":{"current":3.29,"daily":{"changePct":1.3498152275077894e-14,"direction":"flat"},"weekly":{"changePct":1.3498152275077894e-14,"direction":"flat"},"monthly":{"changePct":-16.823718685359708,"direction":"down"}}}}},"ex2-61":{"variant":"normal","grade":"raw","current":2.8,"daily":{"changePct":3.321033210332098,"direction":"up"},"weekly":{"changePct":1.660516605166049,"direction":"up"},"monthly":{"changePct":3.6023125957405013,"direction":"up"},"allVariants":{"normal":{"raw":{"current":2.8,"daily":{"changePct":3.321033210332098,"direction":"up"},"weekly":{"changePct":1.660516605166049,"direction":"up"},"monthly":{"changePct":3.6023125957405013,"direction":"up"}},"psa10":{"current":69.16,"daily":{"changePct":0,"direction":"flat"},"weekly":{"changePct":-2.0547794556393872e-14,"direction":"flat"},"monthly":{"changePct":-4.1095589112787743e-14,"direction":"flat"}}},"reverseHolofoil":{"raw":{"current":14.54,"daily":{"changePct":0,"direction":"flat"},"weekly":{"changePct":8.426547352721842,"direction":"up"},"monthly":{"changePct":2.4075849579205224,"direction":"up"}}}}},"ex2-62":{"variant":"normal","grade":"raw","current":1.35,"daily":{"changePct":0,"direction":"flat"},"weekly":{"changePct":1.6447748512965283e-14,"direction":"flat"},"monthly":{"changePct":-0.8016032064128471,"direction":"flat"},"allVariants":{"normal":{"raw":{"current":1.35,"daily":{"changePct":0,"direction":"flat"},"weekly":{"changePct":1.6447748512965283e-14,"direction":"flat"},"monthly":{"changePct":-0.8016032064128471,"direction":"flat"}},"psa10":{"current":16.04,"daily":{"changePct":0,"direction":"flat"},"weekly":{"changePct":0,"direction":"flat"},"monthly":{"changePct":-2.2149087773070456e-14,"direction":"flat"}}},"reverseHolofoil":{"raw":{"current":20.15,"daily":{"changePct":0,"direction":"flat"},"weekly":{"changePct":-1.7631333393550872e-14,"direction":"flat"},"monthly":{"changePct":-1.7631333393550866e-14,"direction":"flat"}}}}},"ex2-63":{"variant":"normal","grade":"raw","current":5.97,"daily":{"changePct":-0.9950248756218987,"direction":"flat"},"weekly":{"changePct":18.209963411201805,"direction":"up"},"monthly":{"changePct":7.1975617380431425,"direction":"up"},"allVariants":{"normal":{"raw":{"current":5.97,"daily":{"changePct":-0.9950248756218987,"direction":"flat"},"weekly":{"changePct":18.209963411201805,"direction":"up"},"monthly":{"changePct":7.1975617380431425,"direction":"up"}},"psa10":{"current":82.4,"daily":{"changePct":0,"direction":"flat"},"weekly":{"changePct":0,"direction":"flat"},"monthly":{"changePct":-1.7246182906798547e-14,"direction":"flat"}}},"reverseHolofoil":{"raw":{"current":52.37,"daily":{"changePct":0,"direction":"flat"},"weekly":{"changePct":0,"direction":"flat"},"monthly":{"changePct":2.214375698646176,"direction":"up"}},"psa10":{"current":642,"daily":{"changePct":0,"direction":"flat"},"weekly":{"changePct":1.770823017470655e-14,"direction":"flat"},"monthly":{"changePct":0,"direction":"flat"}}},"nonEreader":{"raw":{"current":5.49,"daily":{"changePct":0.36563071297989874,"direction":"flat"},"weekly":{"changePct":0.1828153564899575,"direction":"flat"},"monthly":{"changePct":-2.570919936189419,"direction":"down"}}}}},"ex2-64":{"variant":"normal","grade":"raw","current":0.45,"daily":{"changePct":-2.1739130434782625,"direction":"down"},"weekly":{"changePct":-2.300613496932519,"direction":"down"},"monthly":{"changePct":-2.577460926789168,"direction":"down"},"allVariants":{"normal":{"raw":{"current":0.45,"daily":{"changePct":-2.1739130434782625,"direction":"down"},"weekly":{"changePct":-2.300613496932519,"direction":"down"},"monthly":{"changePct":-2.577460926789168,"direction":"down"}}},"reverseHolofoil":{"raw":{"current":4.77,"daily":{"changePct":0,"direction":"flat"},"weekly":{"changePct":0,"direction":"flat"},"monthly":{"changePct":-1.9068984856982263,"direction":"down"}},"psa10":{"current":16.5,"daily":{"changePct":0,"direction":"flat"},"weekly":{"changePct":-2.1531598053336366e-14,"direction":"flat"},"monthly":{"changePct":-2.1531598053336366e-14,"direction":"flat"}}}}},"ex2-65":{"variant":"normal","grade":"raw","current":1.72,"daily":{"changePct":0.5847953216374405,"direction":"flat"},"weekly":{"changePct":1.9100169779286862,"direction":"up"},"monthly":{"changePct":-3.164698016492095,"direction":"down"},"allVariants":{"normal":{"raw":{"current":1.72,"daily":{"changePct":0.5847953216374405,"direction":"flat"},"weekly":{"changePct":1.9100169779286862,"direction":"up"},"monthly":{"changePct":-3.164698016492095,"direction":"down"}},"psa10":{"current":185.1,"daily":{"changePct":0,"direction":"flat"},"weekly":{"changePct":52.25259100843693,"direction":"up"},"monthly":{"changePct":107.40855249173926,"direction":"up"}}},"reverseHolofoil":{"raw":{"current":15.66,"daily":{"changePct":1.134327483652778e-14,"direction":"flat"},"weekly":{"changePct":1.134327483652778e-14,"direction":"flat"},"monthly":{"changePct":0,"direction":"flat"}},"psa10":{"current":1248,"daily":{"changePct":0,"direction":"flat"},"weekly":{"changePct":0,"direction":"flat"},"monthly":{"changePct":1.821904450666924e-14,"direction":"flat"}}}}},"ex2-66":{"variant":"normal","grade":"raw","current":1.44,"daily":{"changePct":-0.6896551724137785,"direction":"flat"},"weekly":{"changePct":2.8992878942014237,"direction":"up"},"monthly":{"changePct":1.8860877684407047,"direction":"up"},"allVariants":{"normal":{"raw":{"current":1.44,"daily":{"changePct":-0.6896551724137785,"direction":"flat"},"weekly":{"changePct":2.8992878942014237,"direction":"up"},"monthly":{"changePct":1.8860877684407047,"direction":"up"}}},"reverseHolofoil":{"raw":{"current":8.35,"daily":{"changePct":0,"direction":"flat"},"weekly":{"changePct":0,"direction":"flat"},"monthly":{"changePct":0.5693638453957914,"direction":"flat"}},"psa10":{"current":70,"daily":{"changePct":0,"direction":"flat"},"weekly":{"changePct":0,"direction":"flat"},"monthly":{"changePct":null,"direction":"flat"}}},"michaelGonzalez":{"raw":{"current":6.09,"daily":{"changePct":-1.4584210504107146e-14,"direction":"flat"},"weekly":{"changePct":3.7226277372262513,"direction":"up"},"monthly":{"changePct":6.309944472488634,"direction":"up"}}}}},"ex2-67":{"variant":"normal","grade":"raw","current":1.36,"daily":{"changePct":1.6326809185664067e-14,"direction":"flat"},"weekly":{"changePct":1.384451544195945,"direction":"up"},"monthly":{"changePct":-0.7352941176470595,"direction":"flat"},"allVariants":{"normal":{"raw":{"current":1.36,"daily":{"changePct":1.6326809185664067e-14,"direction":"flat"},"weekly":{"changePct":1.384451544195945,"direction":"up"},"monthly":{"changePct":-0.7352941176470595,"direction":"flat"}},"psa10":{"current":48.97,"daily":{"changePct":0,"direction":"flat"},"weekly":{"changePct":0,"direction":"flat"},"monthly":{"changePct":-1.450975568225649e-14,"direction":"flat"}}},"reverseHolofoil":{"raw":{"current":13.2,"daily":{"changePct":0,"direction":"flat"},"weekly":{"changePct":7.843137254901953,"direction":"up"},"monthly":{"changePct":16.212624584717616,"direction":"up"}}}}},"ex2-68":{"variant":"normal","grade":"raw","current":0.81,"daily":{"changePct":1.3706457094137738e-14,"direction":"flat"},"weekly":{"changePct":1.250000000000001,"direction":"up"},"monthly":{"changePct":0.7004398110441296,"direction":"flat"},"allVariants":{"normal":{"raw":{"current":0.81,"daily":{"changePct":1.3706457094137738e-14,"direction":"flat"},"weekly":{"changePct":1.250000000000001,"direction":"up"},"monthly":{"changePct":0.7004398110441296,"direction":"flat"}},"psa10":{"current":86.89,"daily":{"changePct":0,"direction":"flat"},"weekly":{"changePct":0,"direction":"flat"},"monthly":{"changePct":1.6354994493269658e-14,"direction":"flat"}}},"reverseHolofoil":{"raw":{"current":7.12,"daily":{"changePct":0,"direction":"flat"},"weekly":{"changePct":3.231151615575815,"direction":"up"},"monthly":{"changePct":8.093245666467414,"direction":"up"}},"psa10":{"current":805.2,"daily":{"changePct":null,"direction":"flat"},"weekly":{"changePct":null,"direction":"flat"},"monthly":{"changePct":null,"direction":"flat"}}}}},"ex2-69":{"variant":"normal","grade":"raw","current":0.58,"daily":{"changePct":0,"direction":"flat"},"weekly":{"changePct":1.9141776286640637e-14,"direction":"flat"},"monthly":{"changePct":1.1093502377179252,"direction":"up"},"allVariants":{"normal":{"raw":{"current":0.58,"daily":{"changePct":0,"direction":"flat"},"weekly":{"changePct":1.9141776286640637e-14,"direction":"flat"},"monthly":{"changePct":1.1093502377179252,"direction":"up"}}},"reverseHolofoil":{"raw":{"current":5.75,"daily":{"changePct":4.545454545454546,"direction":"up"},"weekly":{"changePct":2.272727272727273,"direction":"up"},"monthly":{"changePct":0.6493506493506632,"direction":"flat"}},"psa10":{"current":31.2,"daily":{"changePct":1.1386902816668274e-14,"direction":"flat"},"weekly":{"changePct":0,"direction":"flat"},"monthly":{"changePct":-1.1386902816668274e-14,"direction":"flat"}}},"nonEreader":{"raw":{"current":0.43,"daily":{"changePct":-2.2727272727272747,"direction":"down"},"weekly":{"changePct":-1.1363636363636374,"direction":"down"},"monthly":{"changePct":-0.32467532467531596,"direction":"flat"}}}}},"ex2-7":{"variant":"holofoil","grade":"raw","current":37.85,"daily":{"changePct":0,"direction":"flat"},"weekly":{"changePct":0,"direction":"flat"},"monthly":{"changePct":-1.8772595396568034e-14,"direction":"flat"},"allVariants":{"holofoil":{"raw":{"current":37.85,"daily":{"changePct":0,"direction":"flat"},"weekly":{"changePct":0,"direction":"flat"},"monthly":{"changePct":-1.8772595396568034e-14,"direction":"flat"}},"psa10":{"current":1086.71,"daily":{"changePct":0,"direction":"flat"},"weekly":{"changePct":65.21626757886736,"direction":"up"},"monthly":{"changePct":159.56908609350356,"direction":"up"}}},"reverseHolofoil":{"raw":{"current":35,"daily":{"changePct":0,"direction":"flat"},"weekly":{"changePct":0,"direction":"flat"},"monthly":{"changePct":0.19518542615483228,"direction":"flat"}},"psa10":{"current":700,"daily":{"changePct":-1.6240976817373718e-14,"direction":"flat"},"weekly":{"changePct":1.624097681737372e-14,"direction":"flat"},"monthly":{"changePct":3.248195363474744e-14,"direction":"flat"}}}}},"ex2-70":{"variant":"normal","grade":"raw","current":0.94,"daily":{"changePct":-2.0833333333333353,"direction":"down"},"weekly":{"changePct":1.371951219512188,"direction":"up"},"monthly":{"changePct":1.7892088342185979,"direction":"up"},"allVariants":{"normal":{"raw":{"current":0.94,"daily":{"changePct":-2.0833333333333353,"direction":"down"},"weekly":{"changePct":1.371951219512188,"direction":"up"},"monthly":{"changePct":1.7892088342185979,"direction":"up"}},"psa10":{"current":62,"daily":{"changePct":1.146036670580807e-14,"direction":"flat"},"weekly":{"changePct":2.292073341161614e-14,"direction":"flat"},"monthly":{"changePct":1.146036670580807e-14,"direction":"flat"}}},"reverseHolofoil":{"raw":{"current":5.26,"daily":{"changePct":7.566462167689164,"direction":"up"},"weekly":{"changePct":3.783231083844573,"direction":"up"},"monthly":{"changePct":1.0809231668127666,"direction":"up"}},"psa10":{"current":179.46,"daily":{"changePct":1.583735062431963e-14,"direction":"flat"},"weekly":{"changePct":0,"direction":"flat"},"monthly":{"changePct":-1.5837350624319625e-14,"direction":"flat"}}}}},"ex2-71":{"variant":"normal","grade":"raw","current":0.77,"daily":{"changePct":0,"direction":"flat"},"weekly":{"changePct":1.6981132075471905,"direction":"up"},"monthly":{"changePct":12.841945288753811,"direction":"up"},"allVariants":{"normal":{"raw":{"current":0.77,"daily":{"changePct":0,"direction":"flat"},"weekly":{"changePct":1.6981132075471905,"direction":"up"},"monthly":{"changePct":12.841945288753811,"direction":"up"}},"psa10":{"current":249.31,"daily":{"changePct":0,"direction":"flat"},"weekly":{"changePct":0,"direction":"flat"},"monthly":{"changePct":-1.1400148181141552e-14,"direction":"flat"}}},"reverseHolofoil":{"raw":{"current":11.88,"daily":{"changePct":0,"direction":"flat"},"weekly":{"changePct":0,"direction":"flat"},"monthly":{"changePct":5.693950177935916,"direction":"up"}},"psa10":{"current":58.09,"daily":{"changePct":1.2231756511621625e-14,"direction":"flat"},"weekly":{"changePct":-1.2231756511621623e-14,"direction":"flat"},"monthly":{"changePct":1.2231756511621628e-14,"direction":"flat"}}},"nonEreader":{"raw":{"current":0.72,"daily":{"changePct":0,"direction":"flat"},"weekly":{"changePct":0,"direction":"flat"},"monthly":{"changePct":-1.5419764230904952e-14,"direction":"flat"}}}}},"ex2-72":{"variant":"normal","grade":"raw","current":10.04,"daily":{"changePct":2.763561924257928,"direction":"up"},"weekly":{"changePct":11.650563607085356,"direction":"up"},"monthly":{"changePct":2.8411214953271293,"direction":"up"},"allVariants":{"normal":{"raw":{"current":10.04,"daily":{"changePct":2.763561924257928,"direction":"up"},"weekly":{"changePct":11.650563607085356,"direction":"up"},"monthly":{"changePct":2.8411214953271293,"direction":"up"}},"psa10":{"current":244.98,"daily":{"changePct":1.1601644799740392e-14,"direction":"flat"},"weekly":{"changePct":-47.338132147551256,"direction":"down"},"monthly":{"changePct":-31.841279021730166,"direction":"down"}}},"reverseHolofoil":{"raw":{"current":57.28,"daily":{"changePct":0,"direction":"flat"},"weekly":{"changePct":1.9787374739305228,"direction":"up"},"monthly":{"changePct":7.155551398372427,"direction":"up"}},"psa10":{"current":4182.28,"daily":{"changePct":0,"direction":"flat"},"weekly":{"changePct":60.54148552075701,"direction":"up"},"monthly":{"changePct":63.91001817697662,"direction":"up"}}}}},"ex2-73":{"variant":"normal","grade":"raw","current":13.39,"daily":{"changePct":2.526799387442587,"direction":"up"},"weekly":{"changePct":4.98412338398729,"direction":"up"},"monthly":{"changePct":0.2029742355316737,"direction":"flat"},"allVariants":{"normal":{"raw":{"current":13.39,"daily":{"changePct":2.526799387442587,"direction":"up"},"weekly":{"changePct":4.98412338398729,"direction":"up"},"monthly":{"changePct":0.2029742355316737,"direction":"flat"}},"psa10":{"current":155.45,"daily":{"changePct":0,"direction":"flat"},"weekly":{"changePct":0,"direction":"flat"},"monthly":{"changePct":3.65670111680978e-14,"direction":"flat"}}},"reverseHolofoil":{"raw":{"current":79.13,"daily":{"changePct":0,"direction":"flat"},"weekly":{"changePct":-1.7958871117404273e-14,"direction":"flat"},"monthly":{"changePct":2.9570750978791964,"direction":"up"}},"psa10":{"current":631,"daily":{"changePct":0,"direction":"flat"},"weekly":{"changePct":1.801693149312457e-14,"direction":"flat"},"monthly":{"changePct":0,"direction":"flat"}}}}},"ex2-74":{"variant":"normal","grade":"raw","current":1.78,"daily":{"changePct":0,"direction":"flat"},"weekly":{"changePct":2.3829087921117464,"direction":"up"},"monthly":{"changePct":4.743027042333283,"direction":"up"},"allVariants":{"normal":{"raw":{"current":1.78,"daily":{"changePct":0,"direction":"flat"},"weekly":{"changePct":2.3829087921117464,"direction":"up"},"monthly":{"changePct":4.743027042333283,"direction":"up"}}},"reverseHolofoil":{"raw":{"current":12.5,"daily":{"changePct":0,"direction":"flat"},"weekly":{"changePct":10.062893081761,"direction":"up"},"monthly":{"changePct":13.605442176870788,"direction":"up"}},"psa10":{"current":1500,"daily":{"changePct":0,"direction":"flat"},"weekly":{"changePct":0,"direction":"flat"},"monthly":{"changePct":0,"direction":"flat"}}},"kevinNguyen":{"raw":{"current":4.57,"daily":{"changePct":0,"direction":"flat"},"weekly":{"changePct":0,"direction":"flat"},"monthly":{"changePct":0,"direction":"flat"}}},"nonEreader":{"raw":{"current":1.83,"daily":{"changePct":0,"direction":"flat"},"weekly":{"changePct":2.8089887640449462,"direction":"up"},"monthly":{"changePct":2.2727272727272876,"direction":"up"}}}}},"ex2-75":{"variant":"normal","grade":"raw","current":0.76,"daily":{"changePct":2.7027027027027053,"direction":"up"},"weekly":{"changePct":3.346456692913412,"direction":"up"},"monthly":{"changePct":14.606291324383895,"direction":"up"},"allVariants":{"normal":{"raw":{"current":0.76,"daily":{"changePct":2.7027027027027053,"direction":"up"},"weekly":{"changePct":3.346456692913412,"direction":"up"},"monthly":{"changePct":14.606291324383895,"direction":"up"}},"psa10":{"current":96.13,"daily":{"changePct":0,"direction":"flat"},"weekly":{"changePct":-1.4782955076669097e-14,"direction":"flat"},"monthly":{"changePct":-1.4782955076669097e-14,"direction":"flat"}}},"reverseHolofoil":{"raw":{"current":12.81,"daily":{"changePct":0.5494505494505517,"direction":"flat"},"weekly":{"changePct":0.25224215246636333,"direction":"flat"},"monthly":{"changePct":-0.064129970072678,"direction":"flat"}}}}},"ex2-76":{"variant":"normal","grade":"raw","current":0.48,"daily":{"changePct":0,"direction":"flat"},"weekly":{"changePct":0,"direction":"flat"},"monthly":{"changePct":1.5384615384615246,"direction":"up"},"allVariants":{"normal":{"raw":{"current":0.48,"daily":{"changePct":0,"direction":"flat"},"weekly":{"changePct":0,"direction":"flat"},"monthly":{"changePct":1.5384615384615246,"direction":"up"}},"psa10":{"current":12.11,"daily":{"changePct":0,"direction":"flat"},"weekly":{"changePct":0,"direction":"flat"},"monthly":{"changePct":null,"direction":"flat"}}},"reverseHolofoil":{"raw":{"current":3.64,"daily":{"changePct":0,"direction":"flat"},"weekly":{"changePct":0,"direction":"flat"},"monthly":{"changePct":0,"direction":"flat"}},"psa10":{"current":45.07,"daily":{"changePct":0,"direction":"flat"},"weekly":{"changePct":0,"direction":"flat"},"monthly":{"changePct":null,"direction":"flat"}}}}},"ex2-77":{"variant":"normal","grade":"raw","current":0.69,"daily":{"changePct":0,"direction":"flat"},"weekly":{"changePct":-1.0245901639344226,"direction":"down"},"monthly":{"changePct":-2.6156941649899244,"direction":"down"},"allVariants":{"normal":{"raw":{"current":0.69,"daily":{"changePct":0,"direction":"flat"},"weekly":{"changePct":-1.0245901639344226,"direction":"down"},"monthly":{"changePct":-2.6156941649899244,"direction":"down"}}},"reverseHolofoil":{"raw":{"current":4.8,"daily":{"changePct":1.0526315789473648,"direction":"up"},"weekly":{"changePct":0.526315789473673,"direction":"flat"},"monthly":{"changePct":0.1503759398496048,"direction":"flat"}},"psa10":{"current":55.05,"daily":{"changePct":0,"direction":"flat"},"weekly":{"changePct":0,"direction":"flat"},"monthly":{"changePct":null,"direction":"flat"}}}}},"ex2-78":{"variant":"normal","grade":"raw","current":0.66,"daily":{"changePct":1.5384615384615397,"direction":"up"},"weekly":{"changePct":0.7692307692307871,"direction":"flat"},"monthly":{"changePct":0.21978021978020534,"direction":"flat"},"allVariants":{"normal":{"raw":{"current":0.66,"daily":{"changePct":1.5384615384615397,"direction":"up"},"weekly":{"changePct":0.7692307692307871,"direction":"flat"},"monthly":{"changePct":0.21978021978020534,"direction":"flat"}}},"reverseHolofoil":{"raw":{"current":7.01,"daily":{"changePct":0,"direction":"flat"},"weekly":{"changePct":131.3531353135313,"direction":"up"},"monthly":{"changePct":37.52946723243749,"direction":"up"}},"psa10":{"current":47.46,"daily":{"changePct":1.4971401933419728e-14,"direction":"flat"},"weekly":{"changePct":0,"direction":"flat"},"monthly":{"changePct":null,"direction":"flat"}}}}},"ex2-79":{"variant":"normal","grade":"raw","current":2.96,"daily":{"changePct":0,"direction":"flat"},"weekly":{"changePct":1.5003013846285902e-14,"direction":"flat"},"monthly":{"changePct":0.4524886877828461,"direction":"flat"},"allVariants":{"normal":{"raw":{"current":2.96,"daily":{"changePct":0,"direction":"flat"},"weekly":{"changePct":1.5003013846285902e-14,"direction":"flat"},"monthly":{"changePct":0.4524886877828461,"direction":"flat"}}},"reverseHolofoil":{"raw":{"current":21,"daily":{"changePct":0,"direction":"flat"},"weekly":{"changePct":3.383536836952859e-14,"direction":"flat"},"monthly":{"changePct":2.8991425071458012,"direction":"up"}},"psa10":{"current":499.99,"daily":{"changePct":0,"direction":"flat"},"weekly":{"changePct":1.1368911150384611e-14,"direction":"flat"},"monthly":{"changePct":-1.1368911150384611e-14,"direction":"flat"}}},"kevinNguyen":{"raw":{"current":2.74,"daily":{"changePct":0,"direction":"flat"},"weekly":{"changePct":0,"direction":"flat"},"monthly":{"changePct":-1.6207635395987687e-14,"direction":"flat"}}},"nonEreader":{"raw":{"current":1.52,"daily":{"changePct":0,"direction":"flat"},"weekly":{"changePct":0.37735849056602755,"direction":"flat"},"monthly":{"changePct":1.3333333333333197,"direction":"up"}}}}},"ex2-8":{"variant":"holofoil","grade":"raw","current":23.49,"daily":{"changePct":0,"direction":"flat"},"weekly":{"changePct":0,"direction":"flat"},"monthly":{"changePct":0.027098172808939915,"direction":"flat"},"allVariants":{"holofoil":{"raw":{"current":23.49,"daily":{"changePct":0,"direction":"flat"},"weekly":{"changePct":0,"direction":"flat"},"monthly":{"changePct":0.027098172808939915,"direction":"flat"}},"psa10":{"current":885.45,"daily":{"changePct":0,"direction":"flat"},"weekly":{"changePct":71.71055365478648,"direction":"up"},"monthly":{"changePct":215.297403352698,"direction":"up"}}},"reverseHolofoil":{"raw":{"current":17.04,"daily":{"changePct":0,"direction":"flat"},"weekly":{"changePct":-1.4133399454500293,"direction":"down"},"monthly":{"changePct":-1.3208856650323855,"direction":"down"}}}}},"ex2-80":{"variant":"normal","grade":"raw","current":0.97,"daily":{"changePct":0,"direction":"flat"},"weekly":{"changePct":-0.5856515373352924,"direction":"flat"},"monthly":{"changePct":0.861720748619873,"direction":"flat"},"allVariants":{"normal":{"raw":{"current":0.97,"daily":{"changePct":0,"direction":"flat"},"weekly":{"changePct":-0.5856515373352924,"direction":"flat"},"monthly":{"changePct":0.861720748619873,"direction":"flat"}}},"reverseHolofoil":{"raw":{"current":5.7,"daily":{"changePct":1.558207753859869e-14,"direction":"flat"},"weekly":{"changePct":0,"direction":"flat"},"monthly":{"changePct":1.558207753859869e-14,"direction":"flat"}},"psa10":{"current":84.58,"daily":{"changePct":-1.680167263561362e-14,"direction":"flat"},"weekly":{"changePct":0,"direction":"flat"},"monthly":{"changePct":null,"direction":"flat"}}}}},"ex2-81":{"variant":"normal","grade":"raw","current":0.61,"daily":{"changePct":0,"direction":"flat"},"weekly":{"changePct":-6.153846153846143,"direction":"down"},"monthly":{"changePct":-4.254488680718201,"direction":"down"},"allVariants":{"normal":{"raw":{"current":0.61,"daily":{"changePct":0,"direction":"flat"},"weekly":{"changePct":-6.153846153846143,"direction":"down"},"monthly":{"changePct":-4.254488680718201,"direction":"down"}},"psa10":{"current":69.99,"daily":{"changePct":0,"direction":"flat"},"weekly":{"changePct":-2.0304121610518648e-14,"direction":"flat"},"monthly":{"changePct":0,"direction":"flat"}}},"reverseHolofoil":{"raw":{"current":6.23,"daily":{"changePct":0,"direction":"flat"},"weekly":{"changePct":-2.8512950873198235e-14,"direction":"flat"},"monthly":{"changePct":-0.8679299869810524,"direction":"flat"}}}}},"ex2-82":{"variant":"normal","grade":"raw","current":1.17,"daily":{"changePct":0,"direction":"flat"},"weekly":{"changePct":-0.24360535931790794,"direction":"flat"},"monthly":{"changePct":1.1588555019997986,"direction":"up"},"allVariants":{"normal":{"raw":{"current":1.17,"daily":{"changePct":0,"direction":"flat"},"weekly":{"changePct":-0.24360535931790794,"direction":"flat"},"monthly":{"changePct":1.1588555019997986,"direction":"up"}}},"reverseHolofoil":{"raw":{"current":7.75,"daily":{"changePct":1.146036670580807e-14,"direction":"flat"},"weekly":{"changePct":1.005399366970796,"direction":"up"},"monthly":{"changePct":2.0381204000755053,"direction":"up"}},"psa10":{"current":63.06,"daily":{"changePct":1.1267724956550909e-14,"direction":"flat"},"weekly":{"changePct":1.1267724956550909e-14,"direction":"flat"},"monthly":{"changePct":null,"direction":"flat"}}}}},"ex2-83":{"variant":"normal","grade":"raw","current":0.78,"daily":{"changePct":0,"direction":"flat"},"weekly":{"changePct":-0.3649635036496394,"direction":"flat"},"monthly":{"changePct":1.7793594306049714,"direction":"up"},"allVariants":{"normal":{"raw":{"current":0.78,"daily":{"changePct":0,"direction":"flat"},"weekly":{"changePct":-0.3649635036496394,"direction":"flat"},"monthly":{"changePct":1.7793594306049714,"direction":"up"}},"psa10":{"current":78.81,"daily":{"changePct":0,"direction":"flat"},"weekly":{"changePct":-1.8031791289432813e-14,"direction":"flat"},"monthly":{"changePct":0,"direction":"flat"}}},"reverseHolofoil":{"raw":{"current":12.57,"daily":{"changePct":0,"direction":"flat"},"weekly":{"changePct":1.4131717099445114e-14,"direction":"flat"},"monthly":{"changePct":2.8263434198890228e-14,"direction":"flat"}}}}},"ex2-84":{"variant":"normal","grade":"raw","current":0.71,"daily":{"changePct":0,"direction":"flat"},"weekly":{"changePct":1.8442622950819574,"direction":"up"},"monthly":{"changePct":3.7815126050420305,"direction":"up"},"allVariants":{"normal":{"raw":{"current":0.71,"daily":{"changePct":0,"direction":"flat"},"weekly":{"changePct":1.8442622950819574,"direction":"up"},"monthly":{"changePct":3.7815126050420305,"direction":"up"}},"psa10":{"current":62,"daily":{"changePct":1.146036670580807e-14,"direction":"flat"},"weekly":{"changePct":2.292073341161614e-14,"direction":"flat"},"monthly":{"changePct":1.146036670580807e-14,"direction":"flat"}}},"reverseHolofoil":{"raw":{"current":6.34,"daily":{"changePct":0,"direction":"flat"},"weekly":{"changePct":0,"direction":"flat"},"monthly":{"changePct":-1.4009123339118694e-14,"direction":"flat"}},"psa10":{"current":425,"daily":{"changePct":0,"direction":"flat"},"weekly":{"changePct":0,"direction":"flat"},"monthly":{"changePct":null,"direction":"flat"}}}}},"ex2-85":{"variant":"normal","grade":"raw","current":0.65,"daily":{"changePct":-1.5151515151515165,"direction":"down"},"weekly":{"changePct":0.32822757111600326,"direction":"flat"},"monthly":{"changePct":2.6010973379394473,"direction":"up"},"allVariants":{"normal":{"raw":{"current":0.65,"daily":{"changePct":-1.5151515151515165,"direction":"down"},"weekly":{"changePct":0.32822757111600326,"direction":"flat"},"monthly":{"changePct":2.6010973379394473,"direction":"up"}},"ace10":{"current":20.22,"daily":{"changePct":0,"direction":"flat"},"weekly":{"changePct":0,"direction":"flat"},"monthly":{"changePct":null,"direction":"flat"}}},"reverseHolofoil":{"raw":{"current":7.56,"daily":{"changePct":0,"direction":"flat"},"weekly":{"changePct":0,"direction":"flat"},"monthly":{"changePct":1.1748391794975203e-14,"direction":"flat"}},"psa10":{"current":8,"daily":{"changePct":0,"direction":"flat"},"weekly":{"changePct":0,"direction":"flat"},"monthly":{"changePct":null,"direction":"flat"}}}}},"ex2-86":{"variant":"normal","grade":"raw","current":0.35,"daily":{"changePct":0,"direction":"flat"},"weekly":{"changePct":-2.0000000000000235,"direction":"down"},"monthly":{"changePct":-5.019305019304991,"direction":"down"},"allVariants":{"normal":{"raw":{"current":0.35,"daily":{"changePct":0,"direction":"flat"},"weekly":{"changePct":-2.0000000000000235,"direction":"down"},"monthly":{"changePct":-5.019305019304991,"direction":"down"}},"psa10":{"current":8.61,"daily":{"changePct":0,"direction":"flat"},"weekly":{"changePct":0,"direction":"flat"},"monthly":{"changePct":null,"direction":"flat"}}},"reverseHolofoil":{"raw":{"current":2.17,"daily":{"changePct":0,"direction":"flat"},"weekly":{"changePct":-2.315112540192914,"direction":"down"},"monthly":{"changePct":-2.8445006321112034,"direction":"down"}},"psa10":{"current":38,"daily":{"changePct":0,"direction":"flat"},"weekly":{"changePct":0,"direction":"flat"},"monthly":{"changePct":null,"direction":"flat"}}}}},"ex2-87":{"variant":"normal","grade":"raw","current":1.58,"daily":{"changePct":2.5974025974025996,"direction":"up"},"weekly":{"changePct":1.2987012987012998,"direction":"up"},"monthly":{"changePct":-0.39333835467402106,"direction":"flat"},"allVariants":{"normal":{"raw":{"current":1.58,"daily":{"changePct":2.5974025974025996,"direction":"up"},"weekly":{"changePct":1.2987012987012998,"direction":"up"},"monthly":{"changePct":-0.39333835467402106,"direction":"flat"}}},"reverseHolofoil":{"raw":{"current":5.18,"daily":{"changePct":0,"direction":"flat"},"weekly":{"changePct":0,"direction":"flat"},"monthly":{"changePct":0,"direction":"flat"}},"psa10":{"current":200,"daily":{"changePct":0,"direction":"flat"},"weekly":{"changePct":0,"direction":"flat"},"monthly":{"changePct":0,"direction":"flat"}}}}},"ex2-88":{"variant":"normal","grade":"raw","current":7.41,"daily":{"changePct":0,"direction":"flat"},"weekly":{"changePct":1.8856806128462098,"direction":"up"},"monthly":{"changePct":3.682092555332007,"direction":"up"},"allVariants":{"normal":{"raw":{"current":7.41,"daily":{"changePct":0,"direction":"flat"},"weekly":{"changePct":1.8856806128462098,"direction":"up"},"monthly":{"changePct":3.682092555332007,"direction":"up"}}},"reverseHolofoil":{"raw":{"current":24.99,"daily":{"changePct":0,"direction":"flat"},"weekly":{"changePct":-2.843308266346939e-14,"direction":"flat"},"monthly":{"changePct":2.84330826634694e-14,"direction":"flat"}},"psa10":{"current":2500,"daily":{"changePct":0,"direction":"flat"},"weekly":{"changePct":-1.8189894035458562e-14,"direction":"flat"},"monthly":{"changePct":-1.8189894035458562e-14,"direction":"flat"}}},"chrisFulop":{"raw":{"current":1.75,"daily":{"changePct":-1.2688263138573217e-14,"direction":"flat"},"weekly":{"changePct":-2.537652627714643e-14,"direction":"flat"},"monthly":{"changePct":-1.2688263138573215e-14,"direction":"flat"}}},"kevinNguyen":{"raw":{"current":2.16,"daily":{"changePct":0,"direction":"flat"},"weekly":{"changePct":-2.0559685641206597e-14,"direction":"flat"},"monthly":{"changePct":-4.111937128241319e-14,"direction":"flat"}}},"reedWeichler":{"raw":{"current":3.33,"daily":{"changePct":1.3336012307809691e-14,"direction":"flat"},"weekly":{"changePct":-1.3336012307809687e-14,"direction":"flat"},"monthly":{"changePct":0,"direction":"flat"}}}}},"ex2-89":{"variant":"normal","grade":"raw","current":0.65,"daily":{"changePct":-7.142857142857134,"direction":"down"},"weekly":{"changePct":-4.929577464788721,"direction":"down"},"monthly":{"changePct":-1.4084507042253223,"direction":"down"},"allVariants":{"normal":{"raw":{"current":0.65,"daily":{"changePct":-7.142857142857134,"direction":"down"},"weekly":{"changePct":-4.929577464788721,"direction":"down"},"monthly":{"changePct":-1.4084507042253223,"direction":"down"}}},"reverseHolofoil":{"raw":{"current":8.33,"daily":{"changePct":9.174311926605506,"direction":"up"},"weekly":{"changePct":4.587155963302771,"direction":"up"},"monthly":{"changePct":1.310615989515091,"direction":"up"}},"psa10":{"current":50,"daily":{"changePct":0,"direction":"flat"},"weekly":{"changePct":0,"direction":"flat"},"monthly":{"changePct":0,"direction":"flat"}}},"nonEreader":{"raw":{"current":3.85,"daily":{"changePct":-2.2842639593908483,"direction":"down"},"weekly":{"changePct":-1.142131979695452,"direction":"down"},"monthly":{"changePct":-2.2214318049537574,"direction":"down"}}},"reedWeichler":{"raw":{"current":2.63,"daily":{"changePct":0,"direction":"flat"},"weekly":{"changePct":0,"direction":"flat"},"monthly":{"changePct":-1.6885521287074624e-14,"direction":"flat"}}}}},"ex2-9":{"variant":"holofoil","grade":"raw","current":54.65,"daily":{"changePct":0,"direction":"flat"},"weekly":{"changePct":0,"direction":"flat"},"monthly":{"changePct":0,"direction":"flat"},"allVariants":{"holofoil":{"raw":{"current":54.65,"daily":{"changePct":0,"direction":"flat"},"weekly":{"changePct":0,"direction":"flat"},"monthly":{"changePct":0,"direction":"flat"}},"psa10":{"current":998.28,"daily":{"changePct":0,"direction":"flat"},"weekly":{"changePct":48.07195982455021,"direction":"up"},"monthly":{"changePct":98.45916170012806,"direction":"up"}}},"reverseHolofoil":{"raw":{"current":60.32,"daily":{"changePct":0,"direction":"flat"},"weekly":{"changePct":2.35591092758654e-14,"direction":"flat"},"monthly":{"changePct":3.53386639137981e-14,"direction":"flat"}},"psa10":{"current":195.7,"daily":{"changePct":0,"direction":"flat"},"weekly":{"changePct":-1.4523101395198776e-14,"direction":"flat"},"monthly":{"changePct":0,"direction":"flat"}}}}},"ex2-90":{"variant":"normal","grade":"raw","current":0.38,"daily":{"changePct":0,"direction":"flat"},"weekly":{"changePct":1.4608197692436272e-14,"direction":"flat"},"monthly":{"changePct":-0.23866348448688962,"direction":"flat"},"allVariants":{"normal":{"raw":{"current":0.38,"daily":{"changePct":0,"direction":"flat"},"weekly":{"changePct":1.4608197692436272e-14,"direction":"flat"},"monthly":{"changePct":-0.23866348448688962,"direction":"flat"}}},"reverseHolofoil":{"raw":{"current":1.49,"daily":{"changePct":1.4902322478190025e-14,"direction":"flat"},"weekly":{"changePct":-12.719665271966527,"direction":"down"},"monthly":{"changePct":-13.505726934157824,"direction":"down"}},"psa10":{"current":50,"daily":{"changePct":0,"direction":"flat"},"weekly":{"changePct":0,"direction":"flat"},"monthly":{"changePct":0,"direction":"flat"}}}}},"ex2-91":{"variant":"normal","grade":"raw","current":0.67,"daily":{"changePct":0,"direction":"flat"},"weekly":{"changePct":0.8602150537634344,"direction":"flat"},"monthly":{"changePct":3.069823434992001,"direction":"up"},"allVariants":{"normal":{"raw":{"current":0.67,"daily":{"changePct":0,"direction":"flat"},"weekly":{"changePct":0.8602150537634344,"direction":"flat"},"monthly":{"changePct":3.069823434992001,"direction":"up"}}},"reverseHolofoil":{"raw":{"current":2.29,"daily":{"changePct":0,"direction":"flat"},"weekly":{"changePct":0.5015673981191087,"direction":"flat"},"monthly":{"changePct":6.4258486113632385,"direction":"up"}},"psa10":{"current":286,"daily":{"changePct":0,"direction":"flat"},"weekly":{"changePct":-1.9875321280002798e-14,"direction":"flat"},"monthly":{"changePct":0,"direction":"flat"}}}}},"ex2-92":{"variant":"normal","grade":"raw","current":0.33,"daily":{"changePct":0,"direction":"flat"},"weekly":{"changePct":-0.43103448275857575,"direction":"flat"},"monthly":{"changePct":0,"direction":"flat"},"allVariants":{"normal":{"raw":{"current":0.33,"daily":{"changePct":0,"direction":"flat"},"weekly":{"changePct":-0.43103448275857575,"direction":"flat"},"monthly":{"changePct":0,"direction":"flat"}},"psa10":{"current":58.71,"daily":{"changePct":-1.2102584495998978e-14,"direction":"flat"},"weekly":{"changePct":-1.2102584495998978e-14,"direction":"flat"},"monthly":{"changePct":0,"direction":"flat"}}},"reverseHolofoil":{"raw":{"current":1.39,"daily":{"changePct":-2.1126760563380302,"direction":"down"},"weekly":{"changePct":3.092243186582785,"direction":"up"},"monthly":{"changePct":3.091684434968029,"direction":"up"}}}}},"ex2-93":{"variant":"normal","grade":"raw","current":1.22,"daily":{"changePct":0,"direction":"flat"},"weekly":{"changePct":-0.46620046620047173,"direction":"flat"},"monthly":{"changePct":-0.580720092915213,"direction":"flat"},"allVariants":{"normal":{"raw":{"current":1.22,"daily":{"changePct":0,"direction":"flat"},"weekly":{"changePct":-0.46620046620047173,"direction":"flat"},"monthly":{"changePct":-0.580720092915213,"direction":"flat"}},"psa10":{"current":17.12,"daily":{"changePct":0,"direction":"flat"},"weekly":{"changePct":0,"direction":"flat"},"monthly":{"changePct":null,"direction":"flat"}}},"reverseHolofoil":{"raw":{"current":6.11,"daily":{"changePct":0,"direction":"flat"},"weekly":{"changePct":-2.5518341307815153,"direction":"down"},"monthly":{"changePct":-0.729095465937594,"direction":"flat"}},"psa10":{"current":33.19,"daily":{"changePct":0,"direction":"flat"},"weekly":{"changePct":0,"direction":"flat"},"monthly":{"changePct":null,"direction":"flat"}}},"chrisFulop":{"raw":{"current":1.95,"daily":{"changePct":1.1386902816668274e-14,"direction":"flat"},"weekly":{"changePct":0,"direction":"flat"},"monthly":{"changePct":-1.1386902816668274e-14,"direction":"flat"}}},"cosmosHolofoil":{"raw":{"current":13.49,"daily":{"changePct":0,"direction":"flat"},"weekly":{"changePct":0,"direction":"flat"},"monthly":{"changePct":0,"direction":"flat"}}},"reedWeichler":{"raw":{"current":0.75,"daily":{"changePct":0,"direction":"flat"},"weekly":{"changePct":0,"direction":"flat"},"monthly":{"changePct":0,"direction":"flat"}}},"winnerStamp":{"raw":{"current":20.01,"daily":{"changePct":0,"direction":"flat"},"weekly":{"changePct":1.7754691048478268e-14,"direction":"flat"},"monthly":{"changePct":-0.23568870960431312,"direction":"flat"}}}}},"ex2-94":{"variant":"holofoil","grade":"raw","current":138.32,"daily":{"changePct":1.2443273312838448,"direction":"up"},"weekly":{"changePct":2.0261243877096553,"direction":"up"},"monthly":{"changePct":1.9446914744297061,"direction":"up"},"allVariants":{"holofoil":{"raw":{"current":138.32,"daily":{"changePct":1.2443273312838448,"direction":"up"},"weekly":{"changePct":2.0261243877096553,"direction":"up"},"monthly":{"changePct":1.9446914744297061,"direction":"up"}},"psa10":{"current":4842.04,"daily":{"changePct":0,"direction":"flat"},"weekly":{"changePct":0,"direction":"flat"},"monthly":{"changePct":5.713780448133651,"direction":"up"}}}}},"ex2-95":{"variant":"holofoil","grade":"raw","current":71.5,"daily":{"changePct":0,"direction":"flat"},"weekly":{"changePct":-1.9875321280002798e-14,"direction":"flat"},"monthly":{"changePct":0.14260612697037348,"direction":"flat"},"allVariants":{"holofoil":{"raw":{"current":71.5,"daily":{"changePct":0,"direction":"flat"},"weekly":{"changePct":-1.9875321280002798e-14,"direction":"flat"},"monthly":{"changePct":0.14260612697037348,"direction":"flat"}},"psa10":{"current":3247.7,"daily":{"changePct":0,"direction":"flat"},"weekly":{"changePct":47.204246628739874,"direction":"up"},"monthly":{"changePct":83.29292450157911,"direction":"up"}}}}},"ex2-96":{"variant":"holofoil","grade":"raw","current":178.91,"daily":{"changePct":0,"direction":"flat"},"weekly":{"changePct":0,"direction":"flat"},"monthly":{"changePct":1.53592950305434,"direction":"up"},"allVariants":{"holofoil":{"raw":{"current":178.91,"daily":{"changePct":0,"direction":"flat"},"weekly":{"changePct":0,"direction":"flat"},"monthly":{"changePct":1.53592950305434,"direction":"up"}},"psa10":{"current":1840.43,"daily":{"changePct":0,"direction":"flat"},"weekly":{"changePct":1.9999350773252873,"direction":"up"},"monthly":{"changePct":4.109451983591516,"direction":"up"}}},"kevinNguyen":{"raw":{"current":16.77,"daily":{"changePct":0,"direction":"flat"},"weekly":{"changePct":-0.8111533586818854,"direction":"flat"},"monthly":{"changePct":-1.0078105316200725,"direction":"down"}}}}},"ex2-97":{"variant":"holofoil","grade":"raw","current":88.36,"daily":{"changePct":0,"direction":"flat"},"weekly":{"changePct":-3.216580967678135e-14,"direction":"flat"},"monthly":{"changePct":2.898642783035825,"direction":"up"},"allVariants":{"holofoil":{"raw":{"current":88.36,"daily":{"changePct":0,"direction":"flat"},"weekly":{"changePct":-3.216580967678135e-14,"direction":"flat"},"monthly":{"changePct":2.898642783035825,"direction":"up"}},"psa10":{"current":975.72,"daily":{"changePct":0,"direction":"flat"},"weekly":{"changePct":-15.244486580662464,"direction":"down"},"monthly":{"changePct":17.986424676868644,"direction":"up"}}}}},"ex2-98":{"variant":"holofoil","grade":"raw","current":154.76,"daily":{"changePct":0,"direction":"flat"},"weekly":{"changePct":0,"direction":"flat"},"monthly":{"changePct":0.8835817357551266,"direction":"flat"},"allVariants":{"holofoil":{"raw":{"current":154.76,"daily":{"changePct":0,"direction":"flat"},"weekly":{"changePct":0,"direction":"flat"},"monthly":{"changePct":0.8835817357551266,"direction":"flat"}},"psa10":{"current":4874.25,"daily":{"changePct":0,"direction":"flat"},"weekly":{"changePct":45.18634795788714,"direction":"up"},"monthly":{"changePct":235.32601040930766,"direction":"up"}},"ace10":{"current":116.97,"daily":{"changePct":0,"direction":"flat"},"weekly":{"changePct":0,"direction":"flat"},"monthly":{"changePct":null,"direction":"flat"}}}}},"ex2-99":{"variant":"holofoil","grade":"raw","current":155.06,"daily":{"changePct":-2.606620187174176,"direction":"down"},"weekly":{"changePct":-1.3033100935870967,"direction":"down"},"monthly":{"changePct":-0.3723743124534257,"direction":"flat"},"allVariants":{"holofoil":{"raw":{"current":155.06,"daily":{"changePct":-2.606620187174176,"direction":"down"},"weekly":{"changePct":-1.3033100935870967,"direction":"down"},"monthly":{"changePct":-0.3723743124534257,"direction":"flat"}},"psa10":{"current":2400.22,"daily":{"changePct":0,"direction":"flat"},"weekly":{"changePct":0,"direction":"flat"},"monthly":{"changePct":0,"direction":"flat"}}}}}}